{"Configs":{"testSuiteType":"dynamic","timeout":10000,"eventSelection":"activation","seed":4,"durations":{"waitStepUpperBound":50,"pressDurationUpperBound":10,"soundDuration":10,"clickDuration":10}},"Networks":{"Network 0":{"id":0,"aF":"TANH","cM":"fullyHidden","tf":"DA5l,1)z.P%ArHb,Ne5H-Stage","Nodes":{"Node 0":{"id":0,"t":"I","aF":"NONE","sprite":"Stage","feature":"Scroll"},"Node 1":{"id":1,"t":"I","aF":"NONE","sprite":"Road1","feature":"X"},"Node 2":{"id":2,"t":"I","aF":"NONE","sprite":"Road1","feature":"Y"},"Node 3":{"id":3,"t":"I","aF":"NONE","sprite":"Road1","feature":"Dir"},"Node 4":{"id":4,"t":"I","aF":"NONE","sprite":"Road1","feature":"Size"},"Node 5":{"id":5,"t":"I","aF":"NONE","sprite":"Road2","feature":"X"},"Node 6":{"id":6,"t":"I","aF":"NONE","sprite":"Road2","feature":"Y"},"Node 7":{"id":7,"t":"I","aF":"NONE","sprite":"Road2","feature":"Dir"},"Node 8":{"id":8,"t":"I","aF":"NONE","sprite":"Road2","feature":"Size"},"Node 9":{"id":9,"t":"I","aF":"NONE","sprite":"Car","feature":"X"},"Node 10":{"id":10,"t":"I","aF":"NONE","sprite":"Car","feature":"Y"},"Node 11":{"id":11,"t":"I","aF":"NONE","sprite":"Car","feature":"Dir"},"Node 12":{"id":12,"t":"I","aF":"NONE","sprite":"Car","feature":"Size"},"Node 13":{"id":13,"t":"I","aF":"NONE","sprite":"Car","feature":"Costume"},"Node 14":{"id":14,"t":"I","aF":"NONE","sprite":"Gobo","feature":"X"},"Node 15":{"id":15,"t":"I","aF":"NONE","sprite":"Gobo","feature":"Y"},"Node 16":{"id":16,"t":"I","aF":"NONE","sprite":"Gobo","feature":"Size"},"Node 17":{"id":17,"t":"I","aF":"NONE","sprite":"Fabu","feature":"X"},"Node 18":{"id":18,"t":"I","aF":"NONE","sprite":"Fabu","feature":"Y"},"Node 19":{"id":19,"t":"I","aF":"NONE","sprite":"Fabu","feature":"Size"},"Node 20":{"id":20,"t":"I","aF":"NONE","sprite":"Pele","feature":"X"},"Node 21":{"id":21,"t":"I","aF":"NONE","sprite":"Pele","feature":"Y"},"Node 22":{"id":22,"t":"I","aF":"NONE","sprite":"Pele","feature":"Size"},"Node 23":{"id":23,"t":"B","aF":"NONE"},"Node 24":{"id":32,"t":"H","aF":"TANH"},"Node 25":{"id":33,"t":"H","aF":"TANH"},"Node 26":{"id":34,"t":"H","aF":"TANH"},"Node 27":{"id":35,"t":"H","aF":"TANH"},"Node 28":{"id":36,"t":"H","aF":"TANH"},"Node 29":{"id":37,"t":"H","aF":"TANH"},"Node 30":{"id":38,"t":"H","aF":"TANH"},"Node 31":{"id":39,"t":"H","aF":"TANH"},"Node 32":{"id":24,"t":"C","aF":"NONE","event":"KeyPressEvent-right arrow"},"Node 33":{"id":25,"t":"C","aF":"NONE","event":"KeyPressEvent-left arrow"},"Node 34":{"id":26,"t":"C","aF":"NONE","event":"KeyPressEvent-up arrow"},"Node 35":{"id":27,"t":"C","aF":"NONE","event":"WaitEvent"},"Node 36":{"id":28,"t":"R","aF":"NONE","event":"KeyPressEvent-right arrow","eventP":"Steps"},"Node 37":{"id":29,"t":"R","aF":"NONE","event":"KeyPressEvent-left arrow","eventP":"Steps"},"Node 38":{"id":30,"t":"R","aF":"NONE","event":"KeyPressEvent-up arrow","eventP":"Steps"},"Node 39":{"id":31,"t":"R","aF":"NONE","event":"WaitEvent","eventP":"Duration"}},"Cons":{"Con 0":{"s":0,"t":32,"w":0.58349,"e":true,"i":0,"r":false},"Con 1":{"s":32,"t":24,"w":0.51061,"e":true,"i":1,"r":false},"Con 2":{"s":32,"t":25,"w":-0.59122,"e":true,"i":2,"r":false},"Con 3":{"s":32,"t":26,"w":-0.68408,"e":true,"i":3,"r":false},"Con 4":{"s":32,"t":27,"w":0.717,"e":true,"i":4,"r":false},"Con 5":{"s":32,"t":28,"w":-0.58922,"e":true,"i":5,"r":false},"Con 6":{"s":32,"t":29,"w":-0.49346,"e":true,"i":6,"r":false},"Con 7":{"s":32,"t":30,"w":0.72883,"e":true,"i":7,"r":false},"Con 8":{"s":32,"t":31,"w":-1.37933,"e":true,"i":8,"r":false},"Con 9":{"s":1,"t":33,"w":0.3701,"e":true,"i":9,"r":false},"Con 10":{"s":2,"t":33,"w":-1.37301,"e":true,"i":10,"r":false},"Con 11":{"s":3,"t":33,"w":-0.61737,"e":true,"i":11,"r":false},"Con 12":{"s":4,"t":33,"w":0.10866,"e":true,"i":12,"r":false},"Con 13":{"s":33,"t":24,"w":0.75775,"e":true,"i":13,"r":false},"Con 14":{"s":33,"t":25,"w":-0.56881,"e":true,"i":14,"r":false},"Con 15":{"s":33,"t":26,"w":-1.90788,"e":true,"i":15,"r":false},"Con 16":{"s":33,"t":27,"w":0.78899,"e":true,"i":16,"r":false},"Con 17":{"s":33,"t":28,"w":-0.32951,"e":true,"i":17,"r":false},"Con 18":{"s":33,"t":29,"w":0.66231,"e":true,"i":18,"r":false},"Con 19":{"s":33,"t":30,"w":-1.60144,"e":true,"i":19,"r":false},"Con 20":{"s":33,"t":31,"w":1.15968,"e":true,"i":20,"r":false},"Con 21":{"s":5,"t":34,"w":1.06553,"e":true,"i":21,"r":false},"Con 22":{"s":6,"t":34,"w":1.27281,"e":true,"i":22,"r":false},"Con 23":{"s":7,"t":34,"w":0.47905,"e":true,"i":23,"r":false},"Con 24":{"s":8,"t":34,"w":0.39676,"e":true,"i":24,"r":false},"Con 25":{"s":34,"t":24,"w":-2.39841,"e":true,"i":25,"r":false},"Con 26":{"s":34,"t":25,"w":0.26307,"e":true,"i":26,"r":false},"Con 27":{"s":34,"t":26,"w":0.3067,"e":true,"i":27,"r":false},"Con 28":{"s":34,"t":27,"w":-0.91848,"e":true,"i":28,"r":false},"Con 29":{"s":34,"t":28,"w":1.4214,"e":true,"i":29,"r":false},"Con 30":{"s":34,"t":29,"w":1.07423,"e":true,"i":30,"r":false},"Con 31":{"s":34,"t":30,"w":-0.33578,"e":true,"i":31,"r":false},"Con 32":{"s":34,"t":31,"w":-0.35122,"e":true,"i":32,"r":false},"Con 33":{"s":9,"t":35,"w":0.31946,"e":true,"i":33,"r":false},"Con 34":{"s":10,"t":35,"w":-1.05833,"e":true,"i":34,"r":false},"Con 35":{"s":11,"t":35,"w":-1.46737,"e":true,"i":35,"r":false},"Con 36":{"s":12,"t":35,"w":0.03223,"e":true,"i":36,"r":false},"Con 37":{"s":13,"t":35,"w":-2.07049,"e":true,"i":37,"r":false},"Con 38":{"s":35,"t":24,"w":-1.59305,"e":true,"i":38,"r":false},"Con 39":{"s":35,"t":25,"w":-1.972,"e":true,"i":39,"r":false},"Con 40":{"s":35,"t":26,"w":-1.09072,"e":true,"i":40,"r":false},"Con 41":{"s":35,"t":27,"w":-0.2383,"e":true,"i":41,"r":false},"Con 42":{"s":35,"t":28,"w":-0.12761,"e":true,"i":42,"r":false},"Con 43":{"s":35,"t":29,"w":0.09447,"e":true,"i":43,"r":false},"Con 44":{"s":35,"t":30,"w":1.14877,"e":true,"i":44,"r":false},"Con 45":{"s":35,"t":31,"w":0.10829,"e":true,"i":45,"r":false},"Con 46":{"s":14,"t":36,"w":0.07965,"e":true,"i":46,"r":false},"Con 47":{"s":15,"t":36,"w":-0.98216,"e":true,"i":47,"r":false},"Con 48":{"s":16,"t":36,"w":-1.00134,"e":true,"i":48,"r":false},"Con 49":{"s":36,"t":24,"w":0.51142,"e":true,"i":49,"r":false},"Con 50":{"s":36,"t":25,"w":0.23869,"e":true,"i":50,"r":false},"Con 51":{"s":36,"t":26,"w":-0.35588,"e":true,"i":51,"r":false},"Con 52":{"s":36,"t":27,"w":0.78954,"e":true,"i":52,"r":false},"Con 53":{"s":36,"t":28,"w":-1.0405,"e":true,"i":53,"r":false},"Con 54":{"s":36,"t":29,"w":0.80577,"e":true,"i":54,"r":false},"Con 55":{"s":36,"t":30,"w":1.6985,"e":true,"i":55,"r":false},"Con 56":{"s":36,"t":31,"w":1.98041,"e":true,"i":56,"r":false},"Con 57":{"s":17,"t":37,"w":-0.41881,"e":true,"i":57,"r":false},"Con 58":{"s":18,"t":37,"w":0.15996,"e":true,"i":58,"r":false},"Con 59":{"s":19,"t":37,"w":-0.34601,"e":true,"i":59,"r":false},"Con 60":{"s":37,"t":24,"w":-1.18521,"e":true,"i":60,"r":false},"Con 61":{"s":37,"t":25,"w":0.28164,"e":true,"i":61,"r":false},"Con 62":{"s":37,"t":26,"w":-0.62968,"e":true,"i":62,"r":false},"Con 63":{"s":37,"t":27,"w":-0.18126,"e":true,"i":63,"r":false},"Con 64":{"s":37,"t":28,"w":-0.46468,"e":true,"i":64,"r":false},"Con 65":{"s":37,"t":29,"w":-0.33935,"e":true,"i":65,"r":false},"Con 66":{"s":37,"t":30,"w":0.61569,"e":true,"i":66,"r":false},"Con 67":{"s":37,"t":31,"w":-0.23087,"e":true,"i":67,"r":false},"Con 68":{"s":20,"t":38,"w":-1.29437,"e":true,"i":68,"r":false},"Con 69":{"s":21,"t":38,"w":1.11718,"e":true,"i":69,"r":false},"Con 70":{"s":22,"t":38,"w":-0.24718,"e":true,"i":70,"r":false},"Con 71":{"s":38,"t":24,"w":0.13023,"e":true,"i":71,"r":false},"Con 72":{"s":38,"t":25,"w":1.75283,"e":true,"i":72,"r":false},"Con 73":{"s":38,"t":26,"w":-0.8822,"e":true,"i":73,"r":false},"Con 74":{"s":38,"t":27,"w":0.97949,"e":true,"i":74,"r":false},"Con 75":{"s":38,"t":28,"w":0.27068,"e":true,"i":75,"r":false},"Con 76":{"s":38,"t":29,"w":-0.83722,"e":true,"i":76,"r":false},"Con 77":{"s":38,"t":30,"w":1.28958,"e":true,"i":77,"r":false},"Con 78":{"s":38,"t":31,"w":0.60702,"e":true,"i":78,"r":false},"Con 79":{"s":23,"t":39,"w":-1.50544,"e":true,"i":79,"r":false},"Con 80":{"s":39,"t":24,"w":-0.43421,"e":true,"i":80,"r":false},"Con 81":{"s":39,"t":25,"w":-1.49625,"e":true,"i":81,"r":false},"Con 82":{"s":39,"t":26,"w":-1.03213,"e":true,"i":82,"r":false},"Con 83":{"s":39,"t":27,"w":-0.50479,"e":true,"i":83,"r":false},"Con 84":{"s":39,"t":28,"w":-1.10303,"e":true,"i":84,"r":false},"Con 85":{"s":39,"t":29,"w":-0.60627,"e":true,"i":85,"r":false},"Con 86":{"s":39,"t":30,"w":-0.25669,"e":true,"i":86,"r":false},"Con 87":{"s":39,"t":31,"w":0.30029,"e":true,"i":87,"r":false}}},"Network 1":{"id":600,"aF":"TANH","cM":"fullyHidden","tf":"5tt3cPFNZP}xOaNwiG_Y-Legs","Nodes":{"Node 0":{"id":0,"t":"I","aF":"NONE","sprite":"Stage","feature":"Scroll"},"Node 1":{"id":1,"t":"I","aF":"NONE","sprite":"Road1","feature":"X"},"Node 2":{"id":2,"t":"I","aF":"NONE","sprite":"Road1","feature":"Y"},"Node 3":{"id":3,"t":"I","aF":"NONE","sprite":"Road1","feature":"Dir"},"Node 4":{"id":4,"t":"I","aF":"NONE","sprite":"Road1","feature":"Size"},"Node 5":{"id":5,"t":"I","aF":"NONE","sprite":"Road2","feature":"X"},"Node 6":{"id":6,"t":"I","aF":"NONE","sprite":"Road2","feature":"Y"},"Node 7":{"id":7,"t":"I","aF":"NONE","sprite":"Road2","feature":"Dir"},"Node 8":{"id":8,"t":"I","aF":"NONE","sprite":"Road2","feature":"Size"},"Node 9":{"id":9,"t":"I","aF":"NONE","sprite":"Car","feature":"X"},"Node 10":{"id":10,"t":"I","aF":"NONE","sprite":"Car","feature":"Y"},"Node 11":{"id":11,"t":"I","aF":"NONE","sprite":"Car","feature":"Dir"},"Node 12":{"id":12,"t":"I","aF":"NONE","sprite":"Car","feature":"Size"},"Node 13":{"id":13,"t":"I","aF":"NONE","sprite":"Car","feature":"Costume"},"Node 14":{"id":14,"t":"I","aF":"NONE","sprite":"Gobo","feature":"X"},"Node 15":{"id":15,"t":"I","aF":"NONE","sprite":"Gobo","feature":"Y"},"Node 16":{"id":16,"t":"I","aF":"NONE","sprite":"Gobo","feature":"Size"},"Node 17":{"id":17,"t":"I","aF":"NONE","sprite":"Fabu","feature":"X"},"Node 18":{"id":18,"t":"I","aF":"NONE","sprite":"Fabu","feature":"Y"},"Node 19":{"id":19,"t":"I","aF":"NONE","sprite":"Fabu","feature":"Size"},"Node 20":{"id":20,"t":"I","aF":"NONE","sprite":"Pele","feature":"X"},"Node 21":{"id":21,"t":"I","aF":"NONE","sprite":"Pele","feature":"Y"},"Node 22":{"id":22,"t":"I","aF":"NONE","sprite":"Pele","feature":"Size"},"Node 23":{"id":62,"t":"I","aF":"NONE","sprite":"Stage","feature":"Time"},"Node 24":{"id":63,"t":"I","aF":"NONE","sprite":"Bush","feature":"X"},"Node 25":{"id":64,"t":"I","aF":"NONE","sprite":"Bush","feature":"Y"},"Node 26":{"id":65,"t":"I","aF":"NONE","sprite":"Bush","feature":"Dir"},"Node 27":{"id":66,"t":"I","aF":"NONE","sprite":"Bush","feature":"Size"},"Node 28":{"id":67,"t":"I","aF":"NONE","sprite":"Bush","feature":"Costume"},"Node 29":{"id":68,"t":"I","aF":"NONE","sprite":"Bush","feature":"DistCarX"},"Node 30":{"id":69,"t":"I","aF":"NONE","sprite":"Bush","feature":"DistCarY"},"Node 31":{"id":70,"t":"I","aF":"NONE","sprite":"Car","feature":"DistFront#000008"},"Node 32":{"id":71,"t":"I","aF":"NONE","sprite":"Car","feature":"DistBack#000008"},"Node 33":{"id":72,"t":"I","aF":"NONE","sprite":"Tower","feature":"X"},"Node 34":{"id":73,"t":"I","aF":"NONE","sprite":"Tower","feature":"Y"},"Node 35":{"id":74,"t":"I","aF":"NONE","sprite":"Tower","feature":"Dir"},"Node 36":{"id":75,"t":"I","aF":"NONE","sprite":"Tower","feature":"Size"},"Node 37":{"id":76,"t":"I","aF":"NONE","sprite":"Tower","feature":"Costume"},"Node 38":{"id":77,"t":"I","aF":"NONE","sprite":"Tower","feature":"DistCarX"},"Node 39":{"id":78,"t":"I","aF":"NONE","sprite":"Tower","feature":"DistCarY"},"Node 40":{"id":23,"t":"B","aF":"NONE"},"Node 41":{"id":32,"t":"H","aF":"TANH"},"Node 42":{"id":33,"t":"H","aF":"TANH"},"Node 43":{"id":34,"t":"H","aF":"TANH"},"Node 44":{"id":35,"t":"H","aF":"TANH"},"Node 45":{"id":36,"t":"H","aF":"TANH"},"Node 46":{"id":37,"t":"H","aF":"TANH"},"Node 47":{"id":38,"t":"H","aF":"TANH"},"Node 48":{"id":39,"t":"H","aF":"TANH"},"Node 49":{"id":24,"t":"C","aF":"NONE","event":"KeyPressEvent-right arrow"},"Node 50":{"id":25,"t":"C","aF":"NONE","event":"KeyPressEvent-left arrow"},"Node 51":{"id":26,"t":"C","aF":"NONE","event":"KeyPressEvent-up arrow"},"Node 52":{"id":27,"t":"C","aF":"NONE","event":"WaitEvent"},"Node 53":{"id":28,"t":"R","aF":"NONE","event":"KeyPressEvent-right arrow","eventP":"Steps"},"Node 54":{"id":29,"t":"R","aF":"NONE","event":"KeyPressEvent-left arrow","eventP":"Steps"},"Node 55":{"id":30,"t":"R","aF":"NONE","event":"KeyPressEvent-up arrow","eventP":"Steps"},"Node 56":{"id":31,"t":"R","aF":"NONE","event":"WaitEvent","eventP":"Duration"}},"Cons":{"Con 0":{"s":0,"t":32,"w":0.58349,"e":true,"i":0,"r":false},"Con 1":{"s":32,"t":24,"w":0.51061,"e":true,"i":1,"r":false},"Con 2":{"s":32,"t":25,"w":-0.59122,"e":true,"i":2,"r":false},"Con 3":{"s":32,"t":26,"w":-0.68408,"e":true,"i":3,"r":false},"Con 4":{"s":32,"t":27,"w":0.717,"e":true,"i":4,"r":false},"Con 5":{"s":32,"t":28,"w":-0.58922,"e":true,"i":5,"r":false},"Con 6":{"s":32,"t":29,"w":-0.49346,"e":true,"i":6,"r":false},"Con 7":{"s":32,"t":30,"w":0.72883,"e":true,"i":7,"r":false},"Con 8":{"s":32,"t":31,"w":-1.37933,"e":true,"i":8,"r":false},"Con 9":{"s":1,"t":33,"w":0.3701,"e":true,"i":9,"r":false},"Con 10":{"s":2,"t":33,"w":-1.37301,"e":true,"i":10,"r":false},"Con 11":{"s":3,"t":33,"w":-0.61737,"e":true,"i":11,"r":false},"Con 12":{"s":4,"t":33,"w":0.10866,"e":true,"i":12,"r":false},"Con 13":{"s":33,"t":24,"w":0.75775,"e":true,"i":13,"r":false},"Con 14":{"s":33,"t":25,"w":-0.56881,"e":true,"i":14,"r":false},"Con 15":{"s":33,"t":26,"w":-1.90788,"e":true,"i":15,"r":false},"Con 16":{"s":33,"t":27,"w":0.78899,"e":true,"i":16,"r":false},"Con 17":{"s":33,"t":28,"w":-0.32951,"e":true,"i":17,"r":false},"Con 18":{"s":33,"t":29,"w":0.66231,"e":true,"i":18,"r":false},"Con 19":{"s":33,"t":30,"w":-1.60144,"e":true,"i":19,"r":false},"Con 20":{"s":33,"t":31,"w":1.15968,"e":true,"i":20,"r":false},"Con 21":{"s":5,"t":34,"w":1.06553,"e":true,"i":21,"r":false},"Con 22":{"s":6,"t":34,"w":1.27281,"e":true,"i":22,"r":false},"Con 23":{"s":7,"t":34,"w":0.47905,"e":true,"i":23,"r":false},"Con 24":{"s":8,"t":34,"w":0.39676,"e":true,"i":24,"r":false},"Con 25":{"s":34,"t":24,"w":-2.39841,"e":true,"i":25,"r":false},"Con 26":{"s":34,"t":25,"w":0.26307,"e":true,"i":26,"r":false},"Con 27":{"s":34,"t":26,"w":0.3067,"e":true,"i":27,"r":false},"Con 28":{"s":34,"t":27,"w":-0.91848,"e":true,"i":28,"r":false},"Con 29":{"s":34,"t":28,"w":1.4214,"e":true,"i":29,"r":false},"Con 30":{"s":34,"t":29,"w":1.07423,"e":true,"i":30,"r":false},"Con 31":{"s":34,"t":30,"w":-0.33578,"e":true,"i":31,"r":false},"Con 32":{"s":34,"t":31,"w":-0.35122,"e":true,"i":32,"r":false},"Con 33":{"s":9,"t":35,"w":0.31946,"e":true,"i":33,"r":false},"Con 34":{"s":10,"t":35,"w":-1.05833,"e":true,"i":34,"r":false},"Con 35":{"s":11,"t":35,"w":-1.46737,"e":true,"i":35,"r":false},"Con 36":{"s":12,"t":35,"w":0.03223,"e":true,"i":36,"r":false},"Con 37":{"s":13,"t":35,"w":-2.07049,"e":true,"i":37,"r":false},"Con 38":{"s":35,"t":24,"w":-1.59305,"e":true,"i":38,"r":false},"Con 39":{"s":35,"t":25,"w":-1.972,"e":true,"i":39,"r":false},"Con 40":{"s":35,"t":26,"w":-1.09072,"e":true,"i":40,"r":false},"Con 41":{"s":35,"t":27,"w":-0.2383,"e":true,"i":41,"r":false},"Con 42":{"s":35,"t":28,"w":-0.12761,"e":true,"i":42,"r":false},"Con 43":{"s":35,"t":29,"w":0.09447,"e":true,"i":43,"r":false},"Con 44":{"s":35,"t":30,"w":1.14877,"e":true,"i":44,"r":false},"Con 45":{"s":35,"t":31,"w":0.10829,"e":true,"i":45,"r":false},"Con 46":{"s":14,"t":36,"w":0.07965,"e":true,"i":46,"r":false},"Con 47":{"s":15,"t":36,"w":-0.98216,"e":true,"i":47,"r":false},"Con 48":{"s":16,"t":36,"w":-1.00134,"e":true,"i":48,"r":false},"Con 49":{"s":36,"t":24,"w":0.51142,"e":true,"i":49,"r":false},"Con 50":{"s":36,"t":25,"w":0.23869,"e":true,"i":50,"r":false},"Con 51":{"s":36,"t":26,"w":-0.35588,"e":true,"i":51,"r":false},"Con 52":{"s":36,"t":27,"w":0.78954,"e":true,"i":52,"r":false},"Con 53":{"s":36,"t":28,"w":-1.0405,"e":true,"i":53,"r":false},"Con 54":{"s":36,"t":29,"w":0.80577,"e":true,"i":54,"r":false},"Con 55":{"s":36,"t":30,"w":1.6985,"e":true,"i":55,"r":false},"Con 56":{"s":36,"t":31,"w":1.98041,"e":true,"i":56,"r":false},"Con 57":{"s":17,"t":37,"w":-0.41881,"e":true,"i":57,"r":false},"Con 58":{"s":18,"t":37,"w":0.15996,"e":true,"i":58,"r":false},"Con 59":{"s":19,"t":37,"w":-0.34601,"e":true,"i":59,"r":false},"Con 60":{"s":37,"t":24,"w":-1.18521,"e":true,"i":60,"r":false},"Con 61":{"s":37,"t":25,"w":0.28164,"e":true,"i":61,"r":false},"Con 62":{"s":37,"t":26,"w":-0.62968,"e":true,"i":62,"r":false},"Con 63":{"s":37,"t":27,"w":-0.18126,"e":true,"i":63,"r":false},"Con 64":{"s":37,"t":28,"w":-0.46468,"e":true,"i":64,"r":false},"Con 65":{"s":37,"t":29,"w":-0.33935,"e":true,"i":65,"r":false},"Con 66":{"s":37,"t":30,"w":0.61569,"e":true,"i":66,"r":false},"Con 67":{"s":37,"t":31,"w":-0.23087,"e":true,"i":67,"r":false},"Con 68":{"s":20,"t":38,"w":-1.29437,"e":true,"i":68,"r":false},"Con 69":{"s":21,"t":38,"w":1.11718,"e":true,"i":69,"r":false},"Con 70":{"s":22,"t":38,"w":-0.24718,"e":true,"i":70,"r":false},"Con 71":{"s":38,"t":24,"w":0.13023,"e":true,"i":71,"r":false},"Con 72":{"s":38,"t":25,"w":1.75283,"e":true,"i":72,"r":false},"Con 73":{"s":38,"t":26,"w":-0.8822,"e":true,"i":73,"r":false},"Con 74":{"s":38,"t":27,"w":0.97949,"e":true,"i":74,"r":false},"Con 75":{"s":38,"t":28,"w":0.27068,"e":true,"i":75,"r":false},"Con 76":{"s":38,"t":29,"w":-0.83722,"e":true,"i":76,"r":false},"Con 77":{"s":38,"t":30,"w":1.28958,"e":true,"i":77,"r":false},"Con 78":{"s":38,"t":31,"w":0.60702,"e":true,"i":78,"r":false},"Con 79":{"s":23,"t":39,"w":-1.50544,"e":true,"i":79,"r":false},"Con 80":{"s":39,"t":24,"w":-0.43421,"e":true,"i":80,"r":false},"Con 81":{"s":39,"t":25,"w":-1.49625,"e":true,"i":81,"r":false},"Con 82":{"s":39,"t":26,"w":-1.03213,"e":true,"i":82,"r":false},"Con 83":{"s":39,"t":27,"w":-0.50479,"e":true,"i":83,"r":false},"Con 84":{"s":39,"t":28,"w":-1.10303,"e":true,"i":84,"r":false},"Con 85":{"s":39,"t":29,"w":-0.60627,"e":true,"i":85,"r":false},"Con 86":{"s":39,"t":30,"w":-0.25669,"e":true,"i":86,"r":false},"Con 87":{"s":39,"t":31,"w":0.30029,"e":true,"i":87,"r":false}}},"Network 2":{"id":900,"aF":"TANH","cM":"fullyHidden","tf":"*+JMmq*=W^r`C88Wx+jM-Road1","Nodes":{"Node 0":{"id":0,"t":"I","aF":"NONE","sprite":"Stage","feature":"Scroll"},"Node 1":{"id":1,"t":"I","aF":"NONE","sprite":"Road1","feature":"X"},"Node 2":{"id":2,"t":"I","aF":"NONE","sprite":"Road1","feature":"Y"},"Node 3":{"id":3,"t":"I","aF":"NONE","sprite":"Road1","feature":"Dir"},"Node 4":{"id":4,"t":"I","aF":"NONE","sprite":"Road1","feature":"Size"},"Node 5":{"id":5,"t":"I","aF":"NONE","sprite":"Road2","feature":"X"},"Node 6":{"id":6,"t":"I","aF":"NONE","sprite":"Road2","feature":"Y"},"Node 7":{"id":7,"t":"I","aF":"NONE","sprite":"Road2","feature":"Dir"},"Node 8":{"id":8,"t":"I","aF":"NONE","sprite":"Road2","feature":"Size"},"Node 9":{"id":9,"t":"I","aF":"NONE","sprite":"Car","feature":"X"},"Node 10":{"id":10,"t":"I","aF":"NONE","sprite":"Car","feature":"Y"},"Node 11":{"id":11,"t":"I","aF":"NONE","sprite":"Car","feature":"Dir"},"Node 12":{"id":12,"t":"I","aF":"NONE","sprite":"Car","feature":"Size"},"Node 13":{"id":13,"t":"I","aF":"NONE","sprite":"Car","feature":"Costume"},"Node 14":{"id":14,"t":"I","aF":"NONE","sprite":"Gobo","feature":"X"},"Node 15":{"id":15,"t":"I","aF":"NONE","sprite":"Gobo","feature":"Y"},"Node 16":{"id":16,"t":"I","aF":"NONE","sprite":"Gobo","feature":"Size"},"Node 17":{"id":17,"t":"I","aF":"NONE","sprite":"Fabu","feature":"X"},"Node 18":{"id":18,"t":"I","aF":"NONE","sprite":"Fabu","feature":"Y"},"Node 19":{"id":19,"t":"I","aF":"NONE","sprite":"Fabu","feature":"Size"},"Node 20":{"id":20,"t":"I","aF":"NONE","sprite":"Pele","feature":"X"},"Node 21":{"id":21,"t":"I","aF":"NONE","sprite":"Pele","feature":"Y"},"Node 22":{"id":22,"t":"I","aF":"NONE","sprite":"Pele","feature":"Size"},"Node 23":{"id":62,"t":"I","aF":"NONE","sprite":"Stage","feature":"Time"},"Node 24":{"id":63,"t":"I","aF":"NONE","sprite":"Bush","feature":"X"},"Node 25":{"id":64,"t":"I","aF":"NONE","sprite":"Bush","feature":"Y"},"Node 26":{"id":65,"t":"I","aF":"NONE","sprite":"Bush","feature":"Dir"},"Node 27":{"id":66,"t":"I","aF":"NONE","sprite":"Bush","feature":"Size"},"Node 28":{"id":67,"t":"I","aF":"NONE","sprite":"Bush","feature":"Costume"},"Node 29":{"id":68,"t":"I","aF":"NONE","sprite":"Bush","feature":"DistCarX"},"Node 30":{"id":69,"t":"I","aF":"NONE","sprite":"Bush","feature":"DistCarY"},"Node 31":{"id":70,"t":"I","aF":"NONE","sprite":"Car","feature":"DistFront#000008"},"Node 32":{"id":92,"t":"I","aF":"NONE","sprite":"Legs","feature":"X"},"Node 33":{"id":93,"t":"I","aF":"NONE","sprite":"Legs","feature":"Y"},"Node 34":{"id":94,"t":"I","aF":"NONE","sprite":"Legs","feature":"Dir"},"Node 35":{"id":95,"t":"I","aF":"NONE","sprite":"Legs","feature":"Size"},"Node 36":{"id":96,"t":"I","aF":"NONE","sprite":"Legs","feature":"DistCarX"},"Node 37":{"id":97,"t":"I","aF":"NONE","sprite":"Legs","feature":"DistCarY"},"Node 38":{"id":23,"t":"B","aF":"NONE"},"Node 39":{"id":32,"t":"H","aF":"TANH"},"Node 40":{"id":33,"t":"H","aF":"TANH"},"Node 41":{"id":34,"t":"H","aF":"TANH"},"Node 42":{"id":35,"t":"H","aF":"TANH"},"Node 43":{"id":36,"t":"H","aF":"TANH"},"Node 44":{"id":37,"t":"H","aF":"TANH"},"Node 45":{"id":38,"t":"H","aF":"TANH"},"Node 46":{"id":39,"t":"H","aF":"TANH"},"Node 47":{"id":24,"t":"C","aF":"NONE","event":"KeyPressEvent-right arrow"},"Node 48":{"id":25,"t":"C","aF":"NONE","event":"KeyPressEvent-left arrow"},"Node 49":{"id":26,"t":"C","aF":"NONE","event":"KeyPressEvent-up arrow"},"Node 50":{"id":27,"t":"C","aF":"NONE","event":"WaitEvent"},"Node 51":{"id":28,"t":"R","aF":"NONE","event":"KeyPressEvent-right arrow","eventP":"Steps"},"Node 52":{"id":29,"t":"R","aF":"NONE","event":"KeyPressEvent-left arrow","eventP":"Steps"},"Node 53":{"id":30,"t":"R","aF":"NONE","event":"KeyPressEvent-up arrow","eventP":"Steps"},"Node 54":{"id":31,"t":"R","aF":"NONE","event":"WaitEvent","eventP":"Duration"}},"Cons":{"Con 0":{"s":0,"t":32,"w":0.58349,"e":true,"i":0,"r":false},"Con 1":{"s":32,"t":24,"w":0.51061,"e":true,"i":1,"r":false},"Con 2":{"s":32,"t":25,"w":-0.59122,"e":true,"i":2,"r":false},"Con 3":{"s":32,"t":26,"w":-0.68408,"e":true,"i":3,"r":false},"Con 4":{"s":32,"t":27,"w":0.717,"e":true,"i":4,"r":false},"Con 5":{"s":32,"t":28,"w":-0.58922,"e":true,"i":5,"r":false},"Con 6":{"s":32,"t":29,"w":-0.49346,"e":true,"i":6,"r":false},"Con 7":{"s":32,"t":30,"w":0.72883,"e":true,"i":7,"r":false},"Con 8":{"s":32,"t":31,"w":-1.37933,"e":true,"i":8,"r":false},"Con 9":{"s":1,"t":33,"w":0.3701,"e":true,"i":9,"r":false},"Con 10":{"s":2,"t":33,"w":-1.37301,"e":true,"i":10,"r":false},"Con 11":{"s":3,"t":33,"w":-0.61737,"e":true,"i":11,"r":false},"Con 12":{"s":4,"t":33,"w":0.10866,"e":true,"i":12,"r":false},"Con 13":{"s":33,"t":24,"w":0.75775,"e":true,"i":13,"r":false},"Con 14":{"s":33,"t":25,"w":-0.56881,"e":true,"i":14,"r":false},"Con 15":{"s":33,"t":26,"w":-1.90788,"e":true,"i":15,"r":false},"Con 16":{"s":33,"t":27,"w":0.78899,"e":true,"i":16,"r":false},"Con 17":{"s":33,"t":28,"w":-0.32951,"e":true,"i":17,"r":false},"Con 18":{"s":33,"t":29,"w":0.66231,"e":true,"i":18,"r":false},"Con 19":{"s":33,"t":30,"w":-1.60144,"e":true,"i":19,"r":false},"Con 20":{"s":33,"t":31,"w":1.15968,"e":true,"i":20,"r":false},"Con 21":{"s":5,"t":34,"w":1.06553,"e":true,"i":21,"r":false},"Con 22":{"s":6,"t":34,"w":1.27281,"e":true,"i":22,"r":false},"Con 23":{"s":7,"t":34,"w":0.47905,"e":true,"i":23,"r":false},"Con 24":{"s":8,"t":34,"w":0.39676,"e":true,"i":24,"r":false},"Con 25":{"s":34,"t":24,"w":-2.39841,"e":true,"i":25,"r":false},"Con 26":{"s":34,"t":25,"w":0.26307,"e":true,"i":26,"r":false},"Con 27":{"s":34,"t":26,"w":0.3067,"e":true,"i":27,"r":false},"Con 28":{"s":34,"t":27,"w":-0.91848,"e":true,"i":28,"r":false},"Con 29":{"s":34,"t":28,"w":1.4214,"e":true,"i":29,"r":false},"Con 30":{"s":34,"t":29,"w":1.07423,"e":true,"i":30,"r":false},"Con 31":{"s":34,"t":30,"w":-0.33578,"e":true,"i":31,"r":false},"Con 32":{"s":34,"t":31,"w":-0.35122,"e":true,"i":32,"r":false},"Con 33":{"s":9,"t":35,"w":0.31946,"e":true,"i":33,"r":false},"Con 34":{"s":10,"t":35,"w":-1.05833,"e":true,"i":34,"r":false},"Con 35":{"s":11,"t":35,"w":-1.46737,"e":true,"i":35,"r":false},"Con 36":{"s":12,"t":35,"w":0.03223,"e":true,"i":36,"r":false},"Con 37":{"s":13,"t":35,"w":-2.07049,"e":true,"i":37,"r":false},"Con 38":{"s":35,"t":24,"w":-1.59305,"e":true,"i":38,"r":false},"Con 39":{"s":35,"t":25,"w":-1.972,"e":true,"i":39,"r":false},"Con 40":{"s":35,"t":26,"w":-1.09072,"e":true,"i":40,"r":false},"Con 41":{"s":35,"t":27,"w":-0.2383,"e":true,"i":41,"r":false},"Con 42":{"s":35,"t":28,"w":-0.12761,"e":true,"i":42,"r":false},"Con 43":{"s":35,"t":29,"w":0.09447,"e":true,"i":43,"r":false},"Con 44":{"s":35,"t":30,"w":1.14877,"e":true,"i":44,"r":false},"Con 45":{"s":35,"t":31,"w":0.10829,"e":true,"i":45,"r":false},"Con 46":{"s":14,"t":36,"w":0.07965,"e":true,"i":46,"r":false},"Con 47":{"s":15,"t":36,"w":-0.98216,"e":true,"i":47,"r":false},"Con 48":{"s":16,"t":36,"w":-1.00134,"e":true,"i":48,"r":false},"Con 49":{"s":36,"t":24,"w":0.51142,"e":true,"i":49,"r":false},"Con 50":{"s":36,"t":25,"w":0.23869,"e":true,"i":50,"r":false},"Con 51":{"s":36,"t":26,"w":-0.35588,"e":true,"i":51,"r":false},"Con 52":{"s":36,"t":27,"w":0.78954,"e":true,"i":52,"r":false},"Con 53":{"s":36,"t":28,"w":-1.0405,"e":true,"i":53,"r":false},"Con 54":{"s":36,"t":29,"w":0.80577,"e":true,"i":54,"r":false},"Con 55":{"s":36,"t":30,"w":1.6985,"e":true,"i":55,"r":false},"Con 56":{"s":36,"t":31,"w":1.98041,"e":true,"i":56,"r":false},"Con 57":{"s":17,"t":37,"w":-0.41881,"e":true,"i":57,"r":false},"Con 58":{"s":18,"t":37,"w":0.15996,"e":true,"i":58,"r":false},"Con 59":{"s":19,"t":37,"w":-0.34601,"e":true,"i":59,"r":false},"Con 60":{"s":37,"t":24,"w":-1.18521,"e":true,"i":60,"r":false},"Con 61":{"s":37,"t":25,"w":0.28164,"e":true,"i":61,"r":false},"Con 62":{"s":37,"t":26,"w":-0.62968,"e":true,"i":62,"r":false},"Con 63":{"s":37,"t":27,"w":-0.18126,"e":true,"i":63,"r":false},"Con 64":{"s":37,"t":28,"w":-0.46468,"e":true,"i":64,"r":false},"Con 65":{"s":37,"t":29,"w":-0.33935,"e":true,"i":65,"r":false},"Con 66":{"s":37,"t":30,"w":0.61569,"e":true,"i":66,"r":false},"Con 67":{"s":37,"t":31,"w":-0.23087,"e":true,"i":67,"r":false},"Con 68":{"s":20,"t":38,"w":-1.29437,"e":true,"i":68,"r":false},"Con 69":{"s":21,"t":38,"w":1.11718,"e":true,"i":69,"r":false},"Con 70":{"s":22,"t":38,"w":-0.24718,"e":true,"i":70,"r":false},"Con 71":{"s":38,"t":24,"w":0.13023,"e":true,"i":71,"r":false},"Con 72":{"s":38,"t":25,"w":1.75283,"e":true,"i":72,"r":false},"Con 73":{"s":38,"t":26,"w":-0.8822,"e":true,"i":73,"r":false},"Con 74":{"s":38,"t":27,"w":0.97949,"e":true,"i":74,"r":false},"Con 75":{"s":38,"t":28,"w":0.27068,"e":true,"i":75,"r":false},"Con 76":{"s":38,"t":29,"w":-0.83722,"e":true,"i":76,"r":false},"Con 77":{"s":38,"t":30,"w":1.28958,"e":true,"i":77,"r":false},"Con 78":{"s":38,"t":31,"w":0.60702,"e":true,"i":78,"r":false},"Con 79":{"s":23,"t":39,"w":-1.50544,"e":true,"i":79,"r":false},"Con 80":{"s":39,"t":24,"w":-0.43421,"e":true,"i":80,"r":false},"Con 81":{"s":39,"t":25,"w":-1.49625,"e":true,"i":81,"r":false},"Con 82":{"s":39,"t":26,"w":-1.03213,"e":true,"i":82,"r":false},"Con 83":{"s":39,"t":27,"w":-0.50479,"e":true,"i":83,"r":false},"Con 84":{"s":39,"t":28,"w":-1.10303,"e":true,"i":84,"r":false},"Con 85":{"s":39,"t":29,"w":-0.60627,"e":true,"i":85,"r":false},"Con 86":{"s":39,"t":30,"w":-0.25669,"e":true,"i":86,"r":false},"Con 87":{"s":39,"t":31,"w":0.30029,"e":true,"i":87,"r":false}}},"Network 3":{"id":1800,"aF":"TANH","cM":"fullyHidden","tf":"C#%8dMeGJVY,j*Og3*_y-Tower","Nodes":{"Node 0":{"id":0,"t":"I","aF":"NONE","sprite":"Stage","feature":"Scroll"},"Node 1":{"id":1,"t":"I","aF":"NONE","sprite":"Road1","feature":"X"},"Node 2":{"id":2,"t":"I","aF":"NONE","sprite":"Road1","feature":"Y"},"Node 3":{"id":3,"t":"I","aF":"NONE","sprite":"Road1","feature":"Dir"},"Node 4":{"id":4,"t":"I","aF":"NONE","sprite":"Road1","feature":"Size"},"Node 5":{"id":5,"t":"I","aF":"NONE","sprite":"Road2","feature":"X"},"Node 6":{"id":6,"t":"I","aF":"NONE","sprite":"Road2","feature":"Y"},"Node 7":{"id":7,"t":"I","aF":"NONE","sprite":"Road2","feature":"Dir"},"Node 8":{"id":8,"t":"I","aF":"NONE","sprite":"Road2","feature":"Size"},"Node 9":{"id":9,"t":"I","aF":"NONE","sprite":"Car","feature":"X"},"Node 10":{"id":10,"t":"I","aF":"NONE","sprite":"Car","feature":"Y"},"Node 11":{"id":11,"t":"I","aF":"NONE","sprite":"Car","feature":"Dir"},"Node 12":{"id":12,"t":"I","aF":"NONE","sprite":"Car","feature":"Size"},"Node 13":{"id":13,"t":"I","aF":"NONE","sprite":"Car","feature":"Costume"},"Node 14":{"id":14,"t":"I","aF":"NONE","sprite":"Gobo","feature":"X"},"Node 15":{"id":15,"t":"I","aF":"NONE","sprite":"Gobo","feature":"Y"},"Node 16":{"id":16,"t":"I","aF":"NONE","sprite":"Gobo","feature":"Size"},"Node 17":{"id":17,"t":"I","aF":"NONE","sprite":"Fabu","feature":"X"},"Node 18":{"id":18,"t":"I","aF":"NONE","sprite":"Fabu","feature":"Y"},"Node 19":{"id":19,"t":"I","aF":"NONE","sprite":"Fabu","feature":"Size"},"Node 20":{"id":20,"t":"I","aF":"NONE","sprite":"Pele","feature":"X"},"Node 21":{"id":21,"t":"I","aF":"NONE","sprite":"Pele","feature":"Y"},"Node 22":{"id":22,"t":"I","aF":"NONE","sprite":"Pele","feature":"Size"},"Node 23":{"id":62,"t":"I","aF":"NONE","sprite":"Stage","feature":"Time"},"Node 24":{"id":63,"t":"I","aF":"NONE","sprite":"Bush","feature":"X"},"Node 25":{"id":64,"t":"I","aF":"NONE","sprite":"Bush","feature":"Y"},"Node 26":{"id":65,"t":"I","aF":"NONE","sprite":"Bush","feature":"Dir"},"Node 27":{"id":66,"t":"I","aF":"NONE","sprite":"Bush","feature":"Size"},"Node 28":{"id":67,"t":"I","aF":"NONE","sprite":"Bush","feature":"Costume"},"Node 29":{"id":68,"t":"I","aF":"NONE","sprite":"Bush","feature":"DistCarX"},"Node 30":{"id":69,"t":"I","aF":"NONE","sprite":"Bush","feature":"DistCarY"},"Node 31":{"id":70,"t":"I","aF":"NONE","sprite":"Car","feature":"DistFront#000008"},"Node 32":{"id":71,"t":"I","aF":"NONE","sprite":"Car","feature":"DistBack#000008"},"Node 33":{"id":92,"t":"I","aF":"NONE","sprite":"Legs","feature":"X"},"Node 34":{"id":93,"t":"I","aF":"NONE","sprite":"Legs","feature":"Y"},"Node 35":{"id":94,"t":"I","aF":"NONE","sprite":"Legs","feature":"Dir"},"Node 36":{"id":95,"t":"I","aF":"NONE","sprite":"Legs","feature":"Size"},"Node 37":{"id":96,"t":"I","aF":"NONE","sprite":"Legs","feature":"DistCarX"},"Node 38":{"id":97,"t":"I","aF":"NONE","sprite":"Legs","feature":"DistCarY"},"Node 39":{"id":23,"t":"B","aF":"NONE"},"Node 40":{"id":32,"t":"H","aF":"TANH"},"Node 41":{"id":33,"t":"H","aF":"TANH"},"Node 42":{"id":34,"t":"H","aF":"TANH"},"Node 43":{"id":35,"t":"H","aF":"TANH"},"Node 44":{"id":36,"t":"H","aF":"TANH"},"Node 45":{"id":37,"t":"H","aF":"TANH"},"Node 46":{"id":38,"t":"H","aF":"TANH"},"Node 47":{"id":39,"t":"H","aF":"TANH"},"Node 48":{"id":24,"t":"C","aF":"NONE","event":"KeyPressEvent-right arrow"},"Node 49":{"id":25,"t":"C","aF":"NONE","event":"KeyPressEvent-left arrow"},"Node 50":{"id":26,"t":"C","aF":"NONE","event":"KeyPressEvent-up arrow"},"Node 51":{"id":27,"t":"C","aF":"NONE","event":"WaitEvent"},"Node 52":{"id":28,"t":"R","aF":"NONE","event":"KeyPressEvent-right arrow","eventP":"Steps"},"Node 53":{"id":29,"t":"R","aF":"NONE","event":"KeyPressEvent-left arrow","eventP":"Steps"},"Node 54":{"id":30,"t":"R","aF":"NONE","event":"KeyPressEvent-up arrow","eventP":"Steps"},"Node 55":{"id":31,"t":"R","aF":"NONE","event":"WaitEvent","eventP":"Duration"}},"Cons":{"Con 0":{"s":0,"t":32,"w":0.58349,"e":true,"i":0,"r":false},"Con 1":{"s":32,"t":24,"w":0.51061,"e":true,"i":1,"r":false},"Con 2":{"s":32,"t":25,"w":-0.59122,"e":true,"i":2,"r":false},"Con 3":{"s":32,"t":26,"w":-0.68408,"e":true,"i":3,"r":false},"Con 4":{"s":32,"t":27,"w":0.717,"e":true,"i":4,"r":false},"Con 5":{"s":32,"t":28,"w":-0.58922,"e":true,"i":5,"r":false},"Con 6":{"s":32,"t":29,"w":-0.49346,"e":true,"i":6,"r":false},"Con 7":{"s":32,"t":30,"w":0.72883,"e":true,"i":7,"r":false},"Con 8":{"s":32,"t":31,"w":-1.37933,"e":true,"i":8,"r":false},"Con 9":{"s":1,"t":33,"w":0.3701,"e":true,"i":9,"r":false},"Con 10":{"s":2,"t":33,"w":-1.37301,"e":true,"i":10,"r":false},"Con 11":{"s":3,"t":33,"w":-0.61737,"e":true,"i":11,"r":false},"Con 12":{"s":4,"t":33,"w":0.10866,"e":true,"i":12,"r":false},"Con 13":{"s":33,"t":24,"w":0.75775,"e":true,"i":13,"r":false},"Con 14":{"s":33,"t":25,"w":-0.56881,"e":true,"i":14,"r":false},"Con 15":{"s":33,"t":26,"w":-1.90788,"e":true,"i":15,"r":false},"Con 16":{"s":33,"t":27,"w":0.78899,"e":true,"i":16,"r":false},"Con 17":{"s":33,"t":28,"w":-0.32951,"e":true,"i":17,"r":false},"Con 18":{"s":33,"t":29,"w":0.66231,"e":true,"i":18,"r":false},"Con 19":{"s":33,"t":30,"w":-1.60144,"e":true,"i":19,"r":false},"Con 20":{"s":33,"t":31,"w":1.15968,"e":true,"i":20,"r":false},"Con 21":{"s":5,"t":34,"w":1.06553,"e":true,"i":21,"r":false},"Con 22":{"s":6,"t":34,"w":1.27281,"e":true,"i":22,"r":false},"Con 23":{"s":7,"t":34,"w":0.47905,"e":true,"i":23,"r":false},"Con 24":{"s":8,"t":34,"w":0.39676,"e":true,"i":24,"r":false},"Con 25":{"s":34,"t":24,"w":-2.39841,"e":true,"i":25,"r":false},"Con 26":{"s":34,"t":25,"w":0.26307,"e":true,"i":26,"r":false},"Con 27":{"s":34,"t":26,"w":0.3067,"e":true,"i":27,"r":false},"Con 28":{"s":34,"t":27,"w":-0.91848,"e":true,"i":28,"r":false},"Con 29":{"s":34,"t":28,"w":1.4214,"e":true,"i":29,"r":false},"Con 30":{"s":34,"t":29,"w":1.07423,"e":true,"i":30,"r":false},"Con 31":{"s":34,"t":30,"w":-0.33578,"e":true,"i":31,"r":false},"Con 32":{"s":34,"t":31,"w":-0.35122,"e":true,"i":32,"r":false},"Con 33":{"s":9,"t":35,"w":0.31946,"e":true,"i":33,"r":false},"Con 34":{"s":10,"t":35,"w":-1.05833,"e":true,"i":34,"r":false},"Con 35":{"s":11,"t":35,"w":-1.46737,"e":true,"i":35,"r":false},"Con 36":{"s":12,"t":35,"w":0.03223,"e":true,"i":36,"r":false},"Con 37":{"s":13,"t":35,"w":-2.07049,"e":true,"i":37,"r":false},"Con 38":{"s":35,"t":24,"w":-1.59305,"e":true,"i":38,"r":false},"Con 39":{"s":35,"t":25,"w":-1.972,"e":true,"i":39,"r":false},"Con 40":{"s":35,"t":26,"w":-1.09072,"e":true,"i":40,"r":false},"Con 41":{"s":35,"t":27,"w":-0.2383,"e":true,"i":41,"r":false},"Con 42":{"s":35,"t":28,"w":-0.12761,"e":true,"i":42,"r":false},"Con 43":{"s":35,"t":29,"w":0.09447,"e":true,"i":43,"r":false},"Con 44":{"s":35,"t":30,"w":1.14877,"e":true,"i":44,"r":false},"Con 45":{"s":35,"t":31,"w":0.10829,"e":true,"i":45,"r":false},"Con 46":{"s":14,"t":36,"w":0.07965,"e":true,"i":46,"r":false},"Con 47":{"s":15,"t":36,"w":-0.98216,"e":true,"i":47,"r":false},"Con 48":{"s":16,"t":36,"w":-1.00134,"e":true,"i":48,"r":false},"Con 49":{"s":36,"t":24,"w":0.51142,"e":true,"i":49,"r":false},"Con 50":{"s":36,"t":25,"w":0.23869,"e":true,"i":50,"r":false},"Con 51":{"s":36,"t":26,"w":-0.35588,"e":true,"i":51,"r":false},"Con 52":{"s":36,"t":27,"w":0.78954,"e":true,"i":52,"r":false},"Con 53":{"s":36,"t":28,"w":-1.0405,"e":true,"i":53,"r":false},"Con 54":{"s":36,"t":29,"w":0.80577,"e":true,"i":54,"r":false},"Con 55":{"s":36,"t":30,"w":1.6985,"e":true,"i":55,"r":false},"Con 56":{"s":36,"t":31,"w":1.98041,"e":true,"i":56,"r":false},"Con 57":{"s":17,"t":37,"w":-0.41881,"e":true,"i":57,"r":false},"Con 58":{"s":18,"t":37,"w":0.15996,"e":true,"i":58,"r":false},"Con 59":{"s":19,"t":37,"w":-0.34601,"e":true,"i":59,"r":false},"Con 60":{"s":37,"t":24,"w":-1.18521,"e":true,"i":60,"r":false},"Con 61":{"s":37,"t":25,"w":0.28164,"e":true,"i":61,"r":false},"Con 62":{"s":37,"t":26,"w":-0.62968,"e":true,"i":62,"r":false},"Con 63":{"s":37,"t":27,"w":-0.18126,"e":true,"i":63,"r":false},"Con 64":{"s":37,"t":28,"w":-0.46468,"e":true,"i":64,"r":false},"Con 65":{"s":37,"t":29,"w":-0.33935,"e":true,"i":65,"r":false},"Con 66":{"s":37,"t":30,"w":0.61569,"e":true,"i":66,"r":false},"Con 67":{"s":37,"t":31,"w":-0.23087,"e":true,"i":67,"r":false},"Con 68":{"s":20,"t":38,"w":-1.29437,"e":true,"i":68,"r":false},"Con 69":{"s":21,"t":38,"w":1.11718,"e":true,"i":69,"r":false},"Con 70":{"s":22,"t":38,"w":-0.24718,"e":true,"i":70,"r":false},"Con 71":{"s":38,"t":24,"w":0.13023,"e":true,"i":71,"r":false},"Con 72":{"s":38,"t":25,"w":1.75283,"e":true,"i":72,"r":false},"Con 73":{"s":38,"t":26,"w":-0.8822,"e":true,"i":73,"r":false},"Con 74":{"s":38,"t":27,"w":0.97949,"e":true,"i":74,"r":false},"Con 75":{"s":38,"t":28,"w":0.27068,"e":true,"i":75,"r":false},"Con 76":{"s":38,"t":29,"w":-0.83722,"e":true,"i":76,"r":false},"Con 77":{"s":38,"t":30,"w":1.28958,"e":true,"i":77,"r":false},"Con 78":{"s":38,"t":31,"w":0.60702,"e":true,"i":78,"r":false},"Con 79":{"s":23,"t":39,"w":-1.50544,"e":true,"i":79,"r":false},"Con 80":{"s":39,"t":24,"w":-0.43421,"e":true,"i":80,"r":false},"Con 81":{"s":39,"t":25,"w":-1.49625,"e":true,"i":81,"r":false},"Con 82":{"s":39,"t":26,"w":-1.03213,"e":true,"i":82,"r":false},"Con 83":{"s":39,"t":27,"w":-0.50479,"e":true,"i":83,"r":false},"Con 84":{"s":39,"t":28,"w":-1.10303,"e":true,"i":84,"r":false},"Con 85":{"s":39,"t":29,"w":-0.60627,"e":true,"i":85,"r":false},"Con 86":{"s":39,"t":30,"w":-0.25669,"e":true,"i":86,"r":false},"Con 87":{"s":39,"t":31,"w":0.30029,"e":true,"i":87,"r":false}}},"Network 4":{"id":2100,"aF":"TANH","cM":"fullyHidden","tf":"T.`MB1PLM3%)}]u5{Y-v-Stage","Nodes":{"Node 0":{"id":0,"t":"I","aF":"NONE","sprite":"Stage","feature":"Scroll"},"Node 1":{"id":1,"t":"I","aF":"NONE","sprite":"Road1","feature":"X"},"Node 2":{"id":2,"t":"I","aF":"NONE","sprite":"Road1","feature":"Y"},"Node 3":{"id":3,"t":"I","aF":"NONE","sprite":"Road1","feature":"Dir"},"Node 4":{"id":4,"t":"I","aF":"NONE","sprite":"Road1","feature":"Size"},"Node 5":{"id":5,"t":"I","aF":"NONE","sprite":"Road2","feature":"X"},"Node 6":{"id":6,"t":"I","aF":"NONE","sprite":"Road2","feature":"Y"},"Node 7":{"id":7,"t":"I","aF":"NONE","sprite":"Road2","feature":"Dir"},"Node 8":{"id":8,"t":"I","aF":"NONE","sprite":"Road2","feature":"Size"},"Node 9":{"id":9,"t":"I","aF":"NONE","sprite":"Car","feature":"X"},"Node 10":{"id":10,"t":"I","aF":"NONE","sprite":"Car","feature":"Y"},"Node 11":{"id":11,"t":"I","aF":"NONE","sprite":"Car","feature":"Dir"},"Node 12":{"id":12,"t":"I","aF":"NONE","sprite":"Car","feature":"Size"},"Node 13":{"id":13,"t":"I","aF":"NONE","sprite":"Car","feature":"Costume"},"Node 14":{"id":14,"t":"I","aF":"NONE","sprite":"Gobo","feature":"X"},"Node 15":{"id":15,"t":"I","aF":"NONE","sprite":"Gobo","feature":"Y"},"Node 16":{"id":16,"t":"I","aF":"NONE","sprite":"Gobo","feature":"Size"},"Node 17":{"id":17,"t":"I","aF":"NONE","sprite":"Fabu","feature":"X"},"Node 18":{"id":18,"t":"I","aF":"NONE","sprite":"Fabu","feature":"Y"},"Node 19":{"id":19,"t":"I","aF":"NONE","sprite":"Fabu","feature":"Size"},"Node 20":{"id":20,"t":"I","aF":"NONE","sprite":"Pele","feature":"X"},"Node 21":{"id":21,"t":"I","aF":"NONE","sprite":"Pele","feature":"Y"},"Node 22":{"id":22,"t":"I","aF":"NONE","sprite":"Pele","feature":"Size"},"Node 23":{"id":62,"t":"I","aF":"NONE","sprite":"Stage","feature":"Time"},"Node 24":{"id":63,"t":"I","aF":"NONE","sprite":"Bush","feature":"X"},"Node 25":{"id":64,"t":"I","aF":"NONE","sprite":"Bush","feature":"Y"},"Node 26":{"id":65,"t":"I","aF":"NONE","sprite":"Bush","feature":"Dir"},"Node 27":{"id":66,"t":"I","aF":"NONE","sprite":"Bush","feature":"Size"},"Node 28":{"id":67,"t":"I","aF":"NONE","sprite":"Bush","feature":"Costume"},"Node 29":{"id":68,"t":"I","aF":"NONE","sprite":"Bush","feature":"DistCarX"},"Node 30":{"id":69,"t":"I","aF":"NONE","sprite":"Bush","feature":"DistCarY"},"Node 31":{"id":70,"t":"I","aF":"NONE","sprite":"Car","feature":"DistFront#000008"},"Node 32":{"id":71,"t":"I","aF":"NONE","sprite":"Car","feature":"DistBack#000008"},"Node 33":{"id":72,"t":"I","aF":"NONE","sprite":"Tower","feature":"X"},"Node 34":{"id":73,"t":"I","aF":"NONE","sprite":"Tower","feature":"Y"},"Node 35":{"id":74,"t":"I","aF":"NONE","sprite":"Tower","feature":"Dir"},"Node 36":{"id":75,"t":"I","aF":"NONE","sprite":"Tower","feature":"Size"},"Node 37":{"id":76,"t":"I","aF":"NONE","sprite":"Tower","feature":"Costume"},"Node 38":{"id":77,"t":"I","aF":"NONE","sprite":"Tower","feature":"DistCarX"},"Node 39":{"id":78,"t":"I","aF":"NONE","sprite":"Tower","feature":"DistCarY"},"Node 40":{"id":92,"t":"I","aF":"NONE","sprite":"Legs","feature":"X"},"Node 41":{"id":93,"t":"I","aF":"NONE","sprite":"Legs","feature":"Y"},"Node 42":{"id":94,"t":"I","aF":"NONE","sprite":"Legs","feature":"Dir"},"Node 43":{"id":95,"t":"I","aF":"NONE","sprite":"Legs","feature":"Size"},"Node 44":{"id":96,"t":"I","aF":"NONE","sprite":"Legs","feature":"DistCarX"},"Node 45":{"id":97,"t":"I","aF":"NONE","sprite":"Legs","feature":"DistCarY"},"Node 46":{"id":23,"t":"B","aF":"NONE"},"Node 47":{"id":32,"t":"H","aF":"TANH"},"Node 48":{"id":33,"t":"H","aF":"TANH"},"Node 49":{"id":34,"t":"H","aF":"TANH"},"Node 50":{"id":35,"t":"H","aF":"TANH"},"Node 51":{"id":36,"t":"H","aF":"TANH"},"Node 52":{"id":37,"t":"H","aF":"TANH"},"Node 53":{"id":38,"t":"H","aF":"TANH"},"Node 54":{"id":39,"t":"H","aF":"TANH"},"Node 55":{"id":24,"t":"C","aF":"NONE","event":"KeyPressEvent-right arrow"},"Node 56":{"id":25,"t":"C","aF":"NONE","event":"KeyPressEvent-left arrow"},"Node 57":{"id":26,"t":"C","aF":"NONE","event":"KeyPressEvent-up arrow"},"Node 58":{"id":27,"t":"C","aF":"NONE","event":"WaitEvent"},"Node 59":{"id":28,"t":"R","aF":"NONE","event":"KeyPressEvent-right arrow","eventP":"Steps"},"Node 60":{"id":29,"t":"R","aF":"NONE","event":"KeyPressEvent-left arrow","eventP":"Steps"},"Node 61":{"id":30,"t":"R","aF":"NONE","event":"KeyPressEvent-up arrow","eventP":"Steps"},"Node 62":{"id":31,"t":"R","aF":"NONE","event":"WaitEvent","eventP":"Duration"}},"Cons":{"Con 0":{"s":0,"t":32,"w":0.58349,"e":true,"i":0,"r":false},"Con 1":{"s":32,"t":24,"w":0.51061,"e":true,"i":1,"r":false},"Con 2":{"s":32,"t":25,"w":-0.59122,"e":true,"i":2,"r":false},"Con 3":{"s":32,"t":26,"w":-0.68408,"e":true,"i":3,"r":false},"Con 4":{"s":32,"t":27,"w":0.717,"e":true,"i":4,"r":false},"Con 5":{"s":32,"t":28,"w":-0.58922,"e":true,"i":5,"r":false},"Con 6":{"s":32,"t":29,"w":-0.49346,"e":true,"i":6,"r":false},"Con 7":{"s":32,"t":30,"w":0.72883,"e":true,"i":7,"r":false},"Con 8":{"s":32,"t":31,"w":-1.37933,"e":true,"i":8,"r":false},"Con 9":{"s":1,"t":33,"w":0.3701,"e":true,"i":9,"r":false},"Con 10":{"s":2,"t":33,"w":-1.37301,"e":true,"i":10,"r":false},"Con 11":{"s":3,"t":33,"w":-0.61737,"e":true,"i":11,"r":false},"Con 12":{"s":4,"t":33,"w":0.10866,"e":true,"i":12,"r":false},"Con 13":{"s":33,"t":24,"w":0.75775,"e":true,"i":13,"r":false},"Con 14":{"s":33,"t":25,"w":-0.56881,"e":true,"i":14,"r":false},"Con 15":{"s":33,"t":26,"w":-1.90788,"e":true,"i":15,"r":false},"Con 16":{"s":33,"t":27,"w":0.78899,"e":true,"i":16,"r":false},"Con 17":{"s":33,"t":28,"w":-0.32951,"e":true,"i":17,"r":false},"Con 18":{"s":33,"t":29,"w":0.66231,"e":true,"i":18,"r":false},"Con 19":{"s":33,"t":30,"w":-1.60144,"e":true,"i":19,"r":false},"Con 20":{"s":33,"t":31,"w":1.15968,"e":true,"i":20,"r":false},"Con 21":{"s":5,"t":34,"w":1.06553,"e":true,"i":21,"r":false},"Con 22":{"s":6,"t":34,"w":1.27281,"e":true,"i":22,"r":false},"Con 23":{"s":7,"t":34,"w":0.47905,"e":true,"i":23,"r":false},"Con 24":{"s":8,"t":34,"w":0.39676,"e":true,"i":24,"r":false},"Con 25":{"s":34,"t":24,"w":-2.39841,"e":true,"i":25,"r":false},"Con 26":{"s":34,"t":25,"w":0.26307,"e":true,"i":26,"r":false},"Con 27":{"s":34,"t":26,"w":0.3067,"e":true,"i":27,"r":false},"Con 28":{"s":34,"t":27,"w":-0.91848,"e":true,"i":28,"r":false},"Con 29":{"s":34,"t":28,"w":1.4214,"e":true,"i":29,"r":false},"Con 30":{"s":34,"t":29,"w":1.07423,"e":true,"i":30,"r":false},"Con 31":{"s":34,"t":30,"w":-0.33578,"e":true,"i":31,"r":false},"Con 32":{"s":34,"t":31,"w":-0.35122,"e":true,"i":32,"r":false},"Con 33":{"s":9,"t":35,"w":0.31946,"e":true,"i":33,"r":false},"Con 34":{"s":10,"t":35,"w":-1.05833,"e":true,"i":34,"r":false},"Con 35":{"s":11,"t":35,"w":-1.46737,"e":true,"i":35,"r":false},"Con 36":{"s":12,"t":35,"w":0.03223,"e":true,"i":36,"r":false},"Con 37":{"s":13,"t":35,"w":-2.07049,"e":true,"i":37,"r":false},"Con 38":{"s":35,"t":24,"w":-1.59305,"e":true,"i":38,"r":false},"Con 39":{"s":35,"t":25,"w":-1.972,"e":true,"i":39,"r":false},"Con 40":{"s":35,"t":26,"w":-1.09072,"e":true,"i":40,"r":false},"Con 41":{"s":35,"t":27,"w":-0.2383,"e":true,"i":41,"r":false},"Con 42":{"s":35,"t":28,"w":-0.12761,"e":true,"i":42,"r":false},"Con 43":{"s":35,"t":29,"w":0.09447,"e":true,"i":43,"r":false},"Con 44":{"s":35,"t":30,"w":1.14877,"e":true,"i":44,"r":false},"Con 45":{"s":35,"t":31,"w":0.10829,"e":true,"i":45,"r":false},"Con 46":{"s":14,"t":36,"w":0.07965,"e":true,"i":46,"r":false},"Con 47":{"s":15,"t":36,"w":-0.98216,"e":true,"i":47,"r":false},"Con 48":{"s":16,"t":36,"w":-1.00134,"e":true,"i":48,"r":false},"Con 49":{"s":36,"t":24,"w":0.51142,"e":true,"i":49,"r":false},"Con 50":{"s":36,"t":25,"w":0.23869,"e":true,"i":50,"r":false},"Con 51":{"s":36,"t":26,"w":-0.35588,"e":true,"i":51,"r":false},"Con 52":{"s":36,"t":27,"w":0.78954,"e":true,"i":52,"r":false},"Con 53":{"s":36,"t":28,"w":-1.0405,"e":true,"i":53,"r":false},"Con 54":{"s":36,"t":29,"w":0.80577,"e":true,"i":54,"r":false},"Con 55":{"s":36,"t":30,"w":1.6985,"e":true,"i":55,"r":false},"Con 56":{"s":36,"t":31,"w":1.98041,"e":true,"i":56,"r":false},"Con 57":{"s":17,"t":37,"w":-0.41881,"e":true,"i":57,"r":false},"Con 58":{"s":18,"t":37,"w":0.15996,"e":true,"i":58,"r":false},"Con 59":{"s":19,"t":37,"w":-0.34601,"e":true,"i":59,"r":false},"Con 60":{"s":37,"t":24,"w":-1.18521,"e":true,"i":60,"r":false},"Con 61":{"s":37,"t":25,"w":0.28164,"e":true,"i":61,"r":false},"Con 62":{"s":37,"t":26,"w":-0.62968,"e":true,"i":62,"r":false},"Con 63":{"s":37,"t":27,"w":-0.18126,"e":true,"i":63,"r":false},"Con 64":{"s":37,"t":28,"w":-0.46468,"e":true,"i":64,"r":false},"Con 65":{"s":37,"t":29,"w":-0.33935,"e":true,"i":65,"r":false},"Con 66":{"s":37,"t":30,"w":0.61569,"e":true,"i":66,"r":false},"Con 67":{"s":37,"t":31,"w":-0.23087,"e":true,"i":67,"r":false},"Con 68":{"s":20,"t":38,"w":-1.29437,"e":true,"i":68,"r":false},"Con 69":{"s":21,"t":38,"w":1.11718,"e":true,"i":69,"r":false},"Con 70":{"s":22,"t":38,"w":-0.24718,"e":true,"i":70,"r":false},"Con 71":{"s":38,"t":24,"w":0.13023,"e":true,"i":71,"r":false},"Con 72":{"s":38,"t":25,"w":1.75283,"e":true,"i":72,"r":false},"Con 73":{"s":38,"t":26,"w":-0.8822,"e":true,"i":73,"r":false},"Con 74":{"s":38,"t":27,"w":0.97949,"e":true,"i":74,"r":false},"Con 75":{"s":38,"t":28,"w":0.27068,"e":true,"i":75,"r":false},"Con 76":{"s":38,"t":29,"w":-0.83722,"e":true,"i":76,"r":false},"Con 77":{"s":38,"t":30,"w":1.28958,"e":true,"i":77,"r":false},"Con 78":{"s":38,"t":31,"w":0.60702,"e":true,"i":78,"r":false},"Con 79":{"s":23,"t":39,"w":-1.50544,"e":true,"i":79,"r":false},"Con 80":{"s":39,"t":24,"w":-0.43421,"e":true,"i":80,"r":false},"Con 81":{"s":39,"t":25,"w":-1.49625,"e":true,"i":81,"r":false},"Con 82":{"s":39,"t":26,"w":-1.03213,"e":true,"i":82,"r":false},"Con 83":{"s":39,"t":27,"w":-0.50479,"e":true,"i":83,"r":false},"Con 84":{"s":39,"t":28,"w":-1.10303,"e":true,"i":84,"r":false},"Con 85":{"s":39,"t":29,"w":-0.60627,"e":true,"i":85,"r":false},"Con 86":{"s":39,"t":30,"w":-0.25669,"e":true,"i":86,"r":false},"Con 87":{"s":39,"t":31,"w":0.30029,"e":true,"i":87,"r":false}}},"Network 5":{"id":2400,"aF":"TANH","cM":"fullyHidden","tf":"|Yy=U#)-S}mRso08Nrta-Stage","Nodes":{"Node 0":{"id":0,"t":"I","aF":"NONE","sprite":"Stage","feature":"Scroll"},"Node 1":{"id":1,"t":"I","aF":"NONE","sprite":"Road1","feature":"X"},"Node 2":{"id":2,"t":"I","aF":"NONE","sprite":"Road1","feature":"Y"},"Node 3":{"id":3,"t":"I","aF":"NONE","sprite":"Road1","feature":"Dir"},"Node 4":{"id":4,"t":"I","aF":"NONE","sprite":"Road1","feature":"Size"},"Node 5":{"id":5,"t":"I","aF":"NONE","sprite":"Road2","feature":"X"},"Node 6":{"id":6,"t":"I","aF":"NONE","sprite":"Road2","feature":"Y"},"Node 7":{"id":7,"t":"I","aF":"NONE","sprite":"Road2","feature":"Dir"},"Node 8":{"id":8,"t":"I","aF":"NONE","sprite":"Road2","feature":"Size"},"Node 9":{"id":9,"t":"I","aF":"NONE","sprite":"Car","feature":"X"},"Node 10":{"id":10,"t":"I","aF":"NONE","sprite":"Car","feature":"Y"},"Node 11":{"id":11,"t":"I","aF":"NONE","sprite":"Car","feature":"Dir"},"Node 12":{"id":12,"t":"I","aF":"NONE","sprite":"Car","feature":"Size"},"Node 13":{"id":13,"t":"I","aF":"NONE","sprite":"Car","feature":"Costume"},"Node 14":{"id":14,"t":"I","aF":"NONE","sprite":"Gobo","feature":"X"},"Node 15":{"id":15,"t":"I","aF":"NONE","sprite":"Gobo","feature":"Y"},"Node 16":{"id":16,"t":"I","aF":"NONE","sprite":"Gobo","feature":"Size"},"Node 17":{"id":17,"t":"I","aF":"NONE","sprite":"Fabu","feature":"X"},"Node 18":{"id":18,"t":"I","aF":"NONE","sprite":"Fabu","feature":"Y"},"Node 19":{"id":19,"t":"I","aF":"NONE","sprite":"Fabu","feature":"Size"},"Node 20":{"id":20,"t":"I","aF":"NONE","sprite":"Pele","feature":"X"},"Node 21":{"id":21,"t":"I","aF":"NONE","sprite":"Pele","feature":"Y"},"Node 22":{"id":22,"t":"I","aF":"NONE","sprite":"Pele","feature":"Size"},"Node 23":{"id":62,"t":"I","aF":"NONE","sprite":"Stage","feature":"Time"},"Node 24":{"id":63,"t":"I","aF":"NONE","sprite":"Bush","feature":"X"},"Node 25":{"id":64,"t":"I","aF":"NONE","sprite":"Bush","feature":"Y"},"Node 26":{"id":65,"t":"I","aF":"NONE","sprite":"Bush","feature":"Dir"},"Node 27":{"id":66,"t":"I","aF":"NONE","sprite":"Bush","feature":"Size"},"Node 28":{"id":67,"t":"I","aF":"NONE","sprite":"Bush","feature":"Costume"},"Node 29":{"id":68,"t":"I","aF":"NONE","sprite":"Bush","feature":"DistCarX"},"Node 30":{"id":69,"t":"I","aF":"NONE","sprite":"Bush","feature":"DistCarY"},"Node 31":{"id":70,"t":"I","aF":"NONE","sprite":"Car","feature":"DistFront#000008"},"Node 32":{"id":72,"t":"I","aF":"NONE","sprite":"Tower","feature":"X"},"Node 33":{"id":73,"t":"I","aF":"NONE","sprite":"Tower","feature":"Y"},"Node 34":{"id":74,"t":"I","aF":"NONE","sprite":"Tower","feature":"Dir"},"Node 35":{"id":75,"t":"I","aF":"NONE","sprite":"Tower","feature":"Size"},"Node 36":{"id":76,"t":"I","aF":"NONE","sprite":"Tower","feature":"Costume"},"Node 37":{"id":77,"t":"I","aF":"NONE","sprite":"Tower","feature":"DistCarX"},"Node 38":{"id":78,"t":"I","aF":"NONE","sprite":"Tower","feature":"DistCarY"},"Node 39":{"id":92,"t":"I","aF":"NONE","sprite":"Legs","feature":"X"},"Node 40":{"id":93,"t":"I","aF":"NONE","sprite":"Legs","feature":"Y"},"Node 41":{"id":94,"t":"I","aF":"NONE","sprite":"Legs","feature":"Dir"},"Node 42":{"id":95,"t":"I","aF":"NONE","sprite":"Legs","feature":"Size"},"Node 43":{"id":96,"t":"I","aF":"NONE","sprite":"Legs","feature":"DistCarX"},"Node 44":{"id":97,"t":"I","aF":"NONE","sprite":"Legs","feature":"DistCarY"},"Node 45":{"id":23,"t":"B","aF":"NONE"},"Node 46":{"id":32,"t":"H","aF":"TANH"},"Node 47":{"id":33,"t":"H","aF":"TANH"},"Node 48":{"id":34,"t":"H","aF":"TANH"},"Node 49":{"id":35,"t":"H","aF":"TANH"},"Node 50":{"id":36,"t":"H","aF":"TANH"},"Node 51":{"id":37,"t":"H","aF":"TANH"},"Node 52":{"id":38,"t":"H","aF":"TANH"},"Node 53":{"id":39,"t":"H","aF":"TANH"},"Node 54":{"id":24,"t":"C","aF":"NONE","event":"KeyPressEvent-right arrow"},"Node 55":{"id":25,"t":"C","aF":"NONE","event":"KeyPressEvent-left arrow"},"Node 56":{"id":26,"t":"C","aF":"NONE","event":"KeyPressEvent-up arrow"},"Node 57":{"id":27,"t":"C","aF":"NONE","event":"WaitEvent"},"Node 58":{"id":28,"t":"R","aF":"NONE","event":"KeyPressEvent-right arrow","eventP":"Steps"},"Node 59":{"id":29,"t":"R","aF":"NONE","event":"KeyPressEvent-left arrow","eventP":"Steps"},"Node 60":{"id":30,"t":"R","aF":"NONE","event":"KeyPressEvent-up arrow","eventP":"Steps"},"Node 61":{"id":31,"t":"R","aF":"NONE","event":"WaitEvent","eventP":"Duration"}},"Cons":{"Con 0":{"s":0,"t":32,"w":0.58349,"e":true,"i":0,"r":false},"Con 1":{"s":32,"t":24,"w":0.51061,"e":true,"i":1,"r":false},"Con 2":{"s":32,"t":25,"w":-0.59122,"e":true,"i":2,"r":false},"Con 3":{"s":32,"t":26,"w":-0.68408,"e":true,"i":3,"r":false},"Con 4":{"s":32,"t":27,"w":0.717,"e":true,"i":4,"r":false},"Con 5":{"s":32,"t":28,"w":-0.58922,"e":true,"i":5,"r":false},"Con 6":{"s":32,"t":29,"w":-0.49346,"e":true,"i":6,"r":false},"Con 7":{"s":32,"t":30,"w":0.72883,"e":true,"i":7,"r":false},"Con 8":{"s":32,"t":31,"w":-1.37933,"e":true,"i":8,"r":false},"Con 9":{"s":1,"t":33,"w":0.3701,"e":true,"i":9,"r":false},"Con 10":{"s":2,"t":33,"w":-1.37301,"e":true,"i":10,"r":false},"Con 11":{"s":3,"t":33,"w":-0.61737,"e":true,"i":11,"r":false},"Con 12":{"s":4,"t":33,"w":0.10866,"e":true,"i":12,"r":false},"Con 13":{"s":33,"t":24,"w":0.75775,"e":true,"i":13,"r":false},"Con 14":{"s":33,"t":25,"w":-0.56881,"e":true,"i":14,"r":false},"Con 15":{"s":33,"t":26,"w":-1.90788,"e":true,"i":15,"r":false},"Con 16":{"s":33,"t":27,"w":0.78899,"e":true,"i":16,"r":false},"Con 17":{"s":33,"t":28,"w":-0.32951,"e":true,"i":17,"r":false},"Con 18":{"s":33,"t":29,"w":0.66231,"e":true,"i":18,"r":false},"Con 19":{"s":33,"t":30,"w":-1.60144,"e":true,"i":19,"r":false},"Con 20":{"s":33,"t":31,"w":1.15968,"e":true,"i":20,"r":false},"Con 21":{"s":5,"t":34,"w":1.06553,"e":true,"i":21,"r":false},"Con 22":{"s":6,"t":34,"w":1.27281,"e":true,"i":22,"r":false},"Con 23":{"s":7,"t":34,"w":0.47905,"e":true,"i":23,"r":false},"Con 24":{"s":8,"t":34,"w":0.39676,"e":true,"i":24,"r":false},"Con 25":{"s":34,"t":24,"w":-2.39841,"e":true,"i":25,"r":false},"Con 26":{"s":34,"t":25,"w":0.26307,"e":true,"i":26,"r":false},"Con 27":{"s":34,"t":26,"w":0.3067,"e":true,"i":27,"r":false},"Con 28":{"s":34,"t":27,"w":-0.91848,"e":true,"i":28,"r":false},"Con 29":{"s":34,"t":28,"w":1.4214,"e":true,"i":29,"r":false},"Con 30":{"s":34,"t":29,"w":1.07423,"e":true,"i":30,"r":false},"Con 31":{"s":34,"t":30,"w":-0.33578,"e":true,"i":31,"r":false},"Con 32":{"s":34,"t":31,"w":-0.35122,"e":true,"i":32,"r":false},"Con 33":{"s":9,"t":35,"w":0.31946,"e":true,"i":33,"r":false},"Con 34":{"s":10,"t":35,"w":-1.05833,"e":true,"i":34,"r":false},"Con 35":{"s":11,"t":35,"w":-1.46737,"e":true,"i":35,"r":false},"Con 36":{"s":12,"t":35,"w":0.03223,"e":true,"i":36,"r":false},"Con 37":{"s":13,"t":35,"w":-2.07049,"e":true,"i":37,"r":false},"Con 38":{"s":35,"t":24,"w":-1.59305,"e":true,"i":38,"r":false},"Con 39":{"s":35,"t":25,"w":-1.972,"e":true,"i":39,"r":false},"Con 40":{"s":35,"t":26,"w":-1.09072,"e":true,"i":40,"r":false},"Con 41":{"s":35,"t":27,"w":-0.2383,"e":true,"i":41,"r":false},"Con 42":{"s":35,"t":28,"w":-0.12761,"e":true,"i":42,"r":false},"Con 43":{"s":35,"t":29,"w":0.09447,"e":true,"i":43,"r":false},"Con 44":{"s":35,"t":30,"w":1.14877,"e":true,"i":44,"r":false},"Con 45":{"s":35,"t":31,"w":0.10829,"e":true,"i":45,"r":false},"Con 46":{"s":14,"t":36,"w":0.07965,"e":true,"i":46,"r":false},"Con 47":{"s":15,"t":36,"w":-0.98216,"e":true,"i":47,"r":false},"Con 48":{"s":16,"t":36,"w":-1.00134,"e":true,"i":48,"r":false},"Con 49":{"s":36,"t":24,"w":0.51142,"e":true,"i":49,"r":false},"Con 50":{"s":36,"t":25,"w":0.23869,"e":true,"i":50,"r":false},"Con 51":{"s":36,"t":26,"w":-0.35588,"e":true,"i":51,"r":false},"Con 52":{"s":36,"t":27,"w":0.78954,"e":true,"i":52,"r":false},"Con 53":{"s":36,"t":28,"w":-1.0405,"e":true,"i":53,"r":false},"Con 54":{"s":36,"t":29,"w":0.80577,"e":true,"i":54,"r":false},"Con 55":{"s":36,"t":30,"w":1.6985,"e":true,"i":55,"r":false},"Con 56":{"s":36,"t":31,"w":1.98041,"e":true,"i":56,"r":false},"Con 57":{"s":17,"t":37,"w":-0.41881,"e":true,"i":57,"r":false},"Con 58":{"s":18,"t":37,"w":0.15996,"e":true,"i":58,"r":false},"Con 59":{"s":19,"t":37,"w":-0.34601,"e":true,"i":59,"r":false},"Con 60":{"s":37,"t":24,"w":-1.18521,"e":true,"i":60,"r":false},"Con 61":{"s":37,"t":25,"w":0.28164,"e":true,"i":61,"r":false},"Con 62":{"s":37,"t":26,"w":-0.62968,"e":true,"i":62,"r":false},"Con 63":{"s":37,"t":27,"w":-0.18126,"e":true,"i":63,"r":false},"Con 64":{"s":37,"t":28,"w":-0.46468,"e":true,"i":64,"r":false},"Con 65":{"s":37,"t":29,"w":-0.33935,"e":true,"i":65,"r":false},"Con 66":{"s":37,"t":30,"w":0.61569,"e":true,"i":66,"r":false},"Con 67":{"s":37,"t":31,"w":-0.23087,"e":true,"i":67,"r":false},"Con 68":{"s":20,"t":38,"w":-1.29437,"e":true,"i":68,"r":false},"Con 69":{"s":21,"t":38,"w":1.11718,"e":true,"i":69,"r":false},"Con 70":{"s":22,"t":38,"w":-0.24718,"e":true,"i":70,"r":false},"Con 71":{"s":38,"t":24,"w":0.13023,"e":true,"i":71,"r":false},"Con 72":{"s":38,"t":25,"w":1.75283,"e":true,"i":72,"r":false},"Con 73":{"s":38,"t":26,"w":-0.8822,"e":true,"i":73,"r":false},"Con 74":{"s":38,"t":27,"w":0.97949,"e":true,"i":74,"r":false},"Con 75":{"s":38,"t":28,"w":0.27068,"e":true,"i":75,"r":false},"Con 76":{"s":38,"t":29,"w":-0.83722,"e":true,"i":76,"r":false},"Con 77":{"s":38,"t":30,"w":1.28958,"e":true,"i":77,"r":false},"Con 78":{"s":38,"t":31,"w":0.60702,"e":true,"i":78,"r":false},"Con 79":{"s":23,"t":39,"w":-1.50544,"e":true,"i":79,"r":false},"Con 80":{"s":39,"t":24,"w":-0.43421,"e":true,"i":80,"r":false},"Con 81":{"s":39,"t":25,"w":-1.49625,"e":true,"i":81,"r":false},"Con 82":{"s":39,"t":26,"w":-1.03213,"e":true,"i":82,"r":false},"Con 83":{"s":39,"t":27,"w":-0.50479,"e":true,"i":83,"r":false},"Con 84":{"s":39,"t":28,"w":-1.10303,"e":true,"i":84,"r":false},"Con 85":{"s":39,"t":29,"w":-0.60627,"e":true,"i":85,"r":false},"Con 86":{"s":39,"t":30,"w":-0.25669,"e":true,"i":86,"r":false},"Con 87":{"s":39,"t":31,"w":0.30029,"e":true,"i":87,"r":false}}},"Network 6":{"id":2702,"aF":"TANH","cM":"fullyHidden","tf":"]eo_)gKy,ls*skXXk]@M-Giza","Nodes":{"Node 0":{"id":0,"t":"I","aF":"NONE","sprite":"Stage","feature":"Scroll"},"Node 1":{"id":1,"t":"I","aF":"NONE","sprite":"Road1","feature":"X"},"Node 2":{"id":2,"t":"I","aF":"NONE","sprite":"Road1","feature":"Y"},"Node 3":{"id":3,"t":"I","aF":"NONE","sprite":"Road1","feature":"Dir"},"Node 4":{"id":4,"t":"I","aF":"NONE","sprite":"Road1","feature":"Size"},"Node 5":{"id":5,"t":"I","aF":"NONE","sprite":"Road2","feature":"X"},"Node 6":{"id":6,"t":"I","aF":"NONE","sprite":"Road2","feature":"Y"},"Node 7":{"id":7,"t":"I","aF":"NONE","sprite":"Road2","feature":"Dir"},"Node 8":{"id":8,"t":"I","aF":"NONE","sprite":"Road2","feature":"Size"},"Node 9":{"id":9,"t":"I","aF":"NONE","sprite":"Car","feature":"X"},"Node 10":{"id":10,"t":"I","aF":"NONE","sprite":"Car","feature":"Y"},"Node 11":{"id":11,"t":"I","aF":"NONE","sprite":"Car","feature":"Dir"},"Node 12":{"id":12,"t":"I","aF":"NONE","sprite":"Car","feature":"Size"},"Node 13":{"id":13,"t":"I","aF":"NONE","sprite":"Car","feature":"Costume"},"Node 14":{"id":14,"t":"I","aF":"NONE","sprite":"Gobo","feature":"X"},"Node 15":{"id":15,"t":"I","aF":"NONE","sprite":"Gobo","feature":"Y"},"Node 16":{"id":16,"t":"I","aF":"NONE","sprite":"Gobo","feature":"Size"},"Node 17":{"id":17,"t":"I","aF":"NONE","sprite":"Fabu","feature":"X"},"Node 18":{"id":18,"t":"I","aF":"NONE","sprite":"Fabu","feature":"Y"},"Node 19":{"id":19,"t":"I","aF":"NONE","sprite":"Fabu","feature":"Size"},"Node 20":{"id":20,"t":"I","aF":"NONE","sprite":"Pele","feature":"X"},"Node 21":{"id":21,"t":"I","aF":"NONE","sprite":"Pele","feature":"Y"},"Node 22":{"id":22,"t":"I","aF":"NONE","sprite":"Pele","feature":"Size"},"Node 23":{"id":62,"t":"I","aF":"NONE","sprite":"Stage","feature":"Time"},"Node 24":{"id":63,"t":"I","aF":"NONE","sprite":"Bush","feature":"X"},"Node 25":{"id":64,"t":"I","aF":"NONE","sprite":"Bush","feature":"Y"},"Node 26":{"id":65,"t":"I","aF":"NONE","sprite":"Bush","feature":"Dir"},"Node 27":{"id":66,"t":"I","aF":"NONE","sprite":"Bush","feature":"Size"},"Node 28":{"id":67,"t":"I","aF":"NONE","sprite":"Bush","feature":"Costume"},"Node 29":{"id":68,"t":"I","aF":"NONE","sprite":"Bush","feature":"DistCarX"},"Node 30":{"id":69,"t":"I","aF":"NONE","sprite":"Bush","feature":"DistCarY"},"Node 31":{"id":70,"t":"I","aF":"NONE","sprite":"Car","feature":"DistFront#000008"},"Node 32":{"id":71,"t":"I","aF":"NONE","sprite":"Car","feature":"DistBack#000008"},"Node 33":{"id":72,"t":"I","aF":"NONE","sprite":"Tower","feature":"X"},"Node 34":{"id":73,"t":"I","aF":"NONE","sprite":"Tower","feature":"Y"},"Node 35":{"id":74,"t":"I","aF":"NONE","sprite":"Tower","feature":"Dir"},"Node 36":{"id":75,"t":"I","aF":"NONE","sprite":"Tower","feature":"Size"},"Node 37":{"id":76,"t":"I","aF":"NONE","sprite":"Tower","feature":"Costume"},"Node 38":{"id":77,"t":"I","aF":"NONE","sprite":"Tower","feature":"DistCarX"},"Node 39":{"id":78,"t":"I","aF":"NONE","sprite":"Tower","feature":"DistCarY"},"Node 40":{"id":92,"t":"I","aF":"NONE","sprite":"Legs","feature":"X"},"Node 41":{"id":93,"t":"I","aF":"NONE","sprite":"Legs","feature":"Y"},"Node 42":{"id":94,"t":"I","aF":"NONE","sprite":"Legs","feature":"Dir"},"Node 43":{"id":95,"t":"I","aF":"NONE","sprite":"Legs","feature":"Size"},"Node 44":{"id":96,"t":"I","aF":"NONE","sprite":"Legs","feature":"DistCarX"},"Node 45":{"id":97,"t":"I","aF":"NONE","sprite":"Legs","feature":"DistCarY"},"Node 46":{"id":120,"t":"I","aF":"NONE","sprite":"Stage","feature":"Life"},"Node 47":{"id":23,"t":"B","aF":"NONE"},"Node 48":{"id":32,"t":"H","aF":"TANH"},"Node 49":{"id":33,"t":"H","aF":"TANH"},"Node 50":{"id":34,"t":"H","aF":"TANH"},"Node 51":{"id":35,"t":"H","aF":"TANH"},"Node 52":{"id":36,"t":"H","aF":"TANH"},"Node 53":{"id":37,"t":"H","aF":"TANH"},"Node 54":{"id":38,"t":"H","aF":"TANH"},"Node 55":{"id":39,"t":"H","aF":"TANH"},"Node 56":{"id":24,"t":"C","aF":"NONE","event":"KeyPressEvent-right arrow"},"Node 57":{"id":25,"t":"C","aF":"NONE","event":"KeyPressEvent-left arrow"},"Node 58":{"id":26,"t":"C","aF":"NONE","event":"KeyPressEvent-up arrow"},"Node 59":{"id":27,"t":"C","aF":"NONE","event":"WaitEvent"},"Node 60":{"id":28,"t":"R","aF":"NONE","event":"KeyPressEvent-right arrow","eventP":"Steps"},"Node 61":{"id":29,"t":"R","aF":"NONE","event":"KeyPressEvent-left arrow","eventP":"Steps"},"Node 62":{"id":30,"t":"R","aF":"NONE","event":"KeyPressEvent-up arrow","eventP":"Steps"},"Node 63":{"id":31,"t":"R","aF":"NONE","event":"WaitEvent","eventP":"Duration"}},"Cons":{"Con 0":{"s":0,"t":32,"w":0.58349,"e":true,"i":0,"r":false},"Con 1":{"s":32,"t":24,"w":0.51061,"e":true,"i":1,"r":false},"Con 2":{"s":32,"t":25,"w":-0.59122,"e":true,"i":2,"r":false},"Con 3":{"s":32,"t":26,"w":-0.68408,"e":true,"i":3,"r":false},"Con 4":{"s":32,"t":27,"w":0.717,"e":true,"i":4,"r":false},"Con 5":{"s":32,"t":28,"w":-0.58922,"e":true,"i":5,"r":false},"Con 6":{"s":32,"t":29,"w":-0.49346,"e":true,"i":6,"r":false},"Con 7":{"s":32,"t":30,"w":0.72883,"e":true,"i":7,"r":false},"Con 8":{"s":32,"t":31,"w":-1.37933,"e":true,"i":8,"r":false},"Con 9":{"s":1,"t":33,"w":0.3701,"e":true,"i":9,"r":false},"Con 10":{"s":2,"t":33,"w":-1.37301,"e":true,"i":10,"r":false},"Con 11":{"s":3,"t":33,"w":-0.61737,"e":true,"i":11,"r":false},"Con 12":{"s":4,"t":33,"w":0.10866,"e":true,"i":12,"r":false},"Con 13":{"s":33,"t":24,"w":0.75775,"e":true,"i":13,"r":false},"Con 14":{"s":33,"t":25,"w":-0.56881,"e":true,"i":14,"r":false},"Con 15":{"s":33,"t":26,"w":-1.90788,"e":true,"i":15,"r":false},"Con 16":{"s":33,"t":27,"w":0.78899,"e":true,"i":16,"r":false},"Con 17":{"s":33,"t":28,"w":-0.32951,"e":true,"i":17,"r":false},"Con 18":{"s":33,"t":29,"w":0.66231,"e":true,"i":18,"r":false},"Con 19":{"s":33,"t":30,"w":-1.60144,"e":true,"i":19,"r":false},"Con 20":{"s":33,"t":31,"w":1.15968,"e":true,"i":20,"r":false},"Con 21":{"s":5,"t":34,"w":1.06553,"e":true,"i":21,"r":false},"Con 22":{"s":6,"t":34,"w":1.27281,"e":true,"i":22,"r":false},"Con 23":{"s":7,"t":34,"w":0.47905,"e":true,"i":23,"r":false},"Con 24":{"s":8,"t":34,"w":0.39676,"e":true,"i":24,"r":false},"Con 25":{"s":34,"t":24,"w":-2.39841,"e":true,"i":25,"r":false},"Con 26":{"s":34,"t":25,"w":0.26307,"e":true,"i":26,"r":false},"Con 27":{"s":34,"t":26,"w":0.3067,"e":true,"i":27,"r":false},"Con 28":{"s":34,"t":27,"w":-0.91848,"e":true,"i":28,"r":false},"Con 29":{"s":34,"t":28,"w":1.4214,"e":true,"i":29,"r":false},"Con 30":{"s":34,"t":29,"w":1.07423,"e":true,"i":30,"r":false},"Con 31":{"s":34,"t":30,"w":-0.33578,"e":true,"i":31,"r":false},"Con 32":{"s":34,"t":31,"w":-0.35122,"e":true,"i":32,"r":false},"Con 33":{"s":9,"t":35,"w":0.31946,"e":true,"i":33,"r":false},"Con 34":{"s":10,"t":35,"w":-1.05833,"e":true,"i":34,"r":false},"Con 35":{"s":11,"t":35,"w":-1.46737,"e":true,"i":35,"r":false},"Con 36":{"s":12,"t":35,"w":0.03223,"e":true,"i":36,"r":false},"Con 37":{"s":13,"t":35,"w":-2.07049,"e":true,"i":37,"r":false},"Con 38":{"s":35,"t":24,"w":-1.59305,"e":true,"i":38,"r":false},"Con 39":{"s":35,"t":25,"w":-1.972,"e":true,"i":39,"r":false},"Con 40":{"s":35,"t":26,"w":-1.09072,"e":true,"i":40,"r":false},"Con 41":{"s":35,"t":27,"w":-0.2383,"e":true,"i":41,"r":false},"Con 42":{"s":35,"t":28,"w":-0.12761,"e":true,"i":42,"r":false},"Con 43":{"s":35,"t":29,"w":0.09447,"e":true,"i":43,"r":false},"Con 44":{"s":35,"t":30,"w":1.14877,"e":true,"i":44,"r":false},"Con 45":{"s":35,"t":31,"w":0.10829,"e":true,"i":45,"r":false},"Con 46":{"s":14,"t":36,"w":0.07965,"e":true,"i":46,"r":false},"Con 47":{"s":15,"t":36,"w":-0.98216,"e":true,"i":47,"r":false},"Con 48":{"s":16,"t":36,"w":-1.00134,"e":true,"i":48,"r":false},"Con 49":{"s":36,"t":24,"w":0.51142,"e":true,"i":49,"r":false},"Con 50":{"s":36,"t":25,"w":0.23869,"e":true,"i":50,"r":false},"Con 51":{"s":36,"t":26,"w":-0.35588,"e":true,"i":51,"r":false},"Con 52":{"s":36,"t":27,"w":0.78954,"e":true,"i":52,"r":false},"Con 53":{"s":36,"t":28,"w":-1.0405,"e":true,"i":53,"r":false},"Con 54":{"s":36,"t":29,"w":0.80577,"e":true,"i":54,"r":false},"Con 55":{"s":36,"t":30,"w":1.6985,"e":true,"i":55,"r":false},"Con 56":{"s":36,"t":31,"w":1.98041,"e":true,"i":56,"r":false},"Con 57":{"s":17,"t":37,"w":-0.41881,"e":true,"i":57,"r":false},"Con 58":{"s":18,"t":37,"w":0.15996,"e":true,"i":58,"r":false},"Con 59":{"s":19,"t":37,"w":-0.34601,"e":true,"i":59,"r":false},"Con 60":{"s":37,"t":24,"w":-1.18521,"e":true,"i":60,"r":false},"Con 61":{"s":37,"t":25,"w":0.28164,"e":true,"i":61,"r":false},"Con 62":{"s":37,"t":26,"w":-0.62968,"e":true,"i":62,"r":false},"Con 63":{"s":37,"t":27,"w":-0.18126,"e":true,"i":63,"r":false},"Con 64":{"s":37,"t":28,"w":-0.46468,"e":true,"i":64,"r":false},"Con 65":{"s":37,"t":29,"w":-0.33935,"e":true,"i":65,"r":false},"Con 66":{"s":37,"t":30,"w":0.61569,"e":true,"i":66,"r":false},"Con 67":{"s":37,"t":31,"w":-0.23087,"e":true,"i":67,"r":false},"Con 68":{"s":20,"t":38,"w":-1.29437,"e":true,"i":68,"r":false},"Con 69":{"s":21,"t":38,"w":1.11718,"e":true,"i":69,"r":false},"Con 70":{"s":22,"t":38,"w":-0.24718,"e":true,"i":70,"r":false},"Con 71":{"s":38,"t":24,"w":0.13023,"e":true,"i":71,"r":false},"Con 72":{"s":38,"t":25,"w":1.75283,"e":true,"i":72,"r":false},"Con 73":{"s":38,"t":26,"w":-0.8822,"e":true,"i":73,"r":false},"Con 74":{"s":38,"t":27,"w":0.97949,"e":true,"i":74,"r":false},"Con 75":{"s":38,"t":28,"w":0.27068,"e":true,"i":75,"r":false},"Con 76":{"s":38,"t":29,"w":-0.83722,"e":true,"i":76,"r":false},"Con 77":{"s":38,"t":30,"w":1.28958,"e":true,"i":77,"r":false},"Con 78":{"s":38,"t":31,"w":0.60702,"e":true,"i":78,"r":false},"Con 79":{"s":23,"t":39,"w":-1.50544,"e":true,"i":79,"r":false},"Con 80":{"s":39,"t":24,"w":-0.43421,"e":true,"i":80,"r":false},"Con 81":{"s":39,"t":25,"w":-1.49625,"e":true,"i":81,"r":false},"Con 82":{"s":39,"t":26,"w":-1.03213,"e":true,"i":82,"r":false},"Con 83":{"s":39,"t":27,"w":-0.50479,"e":true,"i":83,"r":false},"Con 84":{"s":39,"t":28,"w":-1.10303,"e":true,"i":84,"r":false},"Con 85":{"s":39,"t":29,"w":-0.60627,"e":true,"i":85,"r":false},"Con 86":{"s":39,"t":30,"w":-0.25669,"e":true,"i":86,"r":false},"Con 87":{"s":39,"t":31,"w":0.30029,"e":true,"i":87,"r":false}}},"Network 7":{"id":3011,"aF":"TANH","cM":"fullyHidden","tf":":?0;D[!Vh;7N(rcxOX#E-Legs","Nodes":{"Node 0":{"id":0,"t":"I","aF":"NONE","sprite":"Stage","feature":"Scroll"},"Node 1":{"id":1,"t":"I","aF":"NONE","sprite":"Road1","feature":"X"},"Node 2":{"id":2,"t":"I","aF":"NONE","sprite":"Road1","feature":"Y"},"Node 3":{"id":3,"t":"I","aF":"NONE","sprite":"Road1","feature":"Dir"},"Node 4":{"id":4,"t":"I","aF":"NONE","sprite":"Road1","feature":"Size"},"Node 5":{"id":5,"t":"I","aF":"NONE","sprite":"Road2","feature":"X"},"Node 6":{"id":6,"t":"I","aF":"NONE","sprite":"Road2","feature":"Y"},"Node 7":{"id":7,"t":"I","aF":"NONE","sprite":"Road2","feature":"Dir"},"Node 8":{"id":8,"t":"I","aF":"NONE","sprite":"Road2","feature":"Size"},"Node 9":{"id":9,"t":"I","aF":"NONE","sprite":"Car","feature":"X"},"Node 10":{"id":10,"t":"I","aF":"NONE","sprite":"Car","feature":"Y"},"Node 11":{"id":11,"t":"I","aF":"NONE","sprite":"Car","feature":"Dir"},"Node 12":{"id":12,"t":"I","aF":"NONE","sprite":"Car","feature":"Size"},"Node 13":{"id":13,"t":"I","aF":"NONE","sprite":"Car","feature":"Costume"},"Node 14":{"id":14,"t":"I","aF":"NONE","sprite":"Gobo","feature":"X"},"Node 15":{"id":15,"t":"I","aF":"NONE","sprite":"Gobo","feature":"Y"},"Node 16":{"id":16,"t":"I","aF":"NONE","sprite":"Gobo","feature":"Size"},"Node 17":{"id":17,"t":"I","aF":"NONE","sprite":"Fabu","feature":"X"},"Node 18":{"id":18,"t":"I","aF":"NONE","sprite":"Fabu","feature":"Y"},"Node 19":{"id":19,"t":"I","aF":"NONE","sprite":"Fabu","feature":"Size"},"Node 20":{"id":20,"t":"I","aF":"NONE","sprite":"Pele","feature":"X"},"Node 21":{"id":21,"t":"I","aF":"NONE","sprite":"Pele","feature":"Y"},"Node 22":{"id":22,"t":"I","aF":"NONE","sprite":"Pele","feature":"Size"},"Node 23":{"id":62,"t":"I","aF":"NONE","sprite":"Stage","feature":"Time"},"Node 24":{"id":63,"t":"I","aF":"NONE","sprite":"Bush","feature":"X"},"Node 25":{"id":64,"t":"I","aF":"NONE","sprite":"Bush","feature":"Y"},"Node 26":{"id":65,"t":"I","aF":"NONE","sprite":"Bush","feature":"Dir"},"Node 27":{"id":66,"t":"I","aF":"NONE","sprite":"Bush","feature":"Size"},"Node 28":{"id":67,"t":"I","aF":"NONE","sprite":"Bush","feature":"Costume"},"Node 29":{"id":68,"t":"I","aF":"NONE","sprite":"Bush","feature":"DistCarX"},"Node 30":{"id":69,"t":"I","aF":"NONE","sprite":"Bush","feature":"DistCarY"},"Node 31":{"id":70,"t":"I","aF":"NONE","sprite":"Car","feature":"DistFront#000008"},"Node 32":{"id":71,"t":"I","aF":"NONE","sprite":"Car","feature":"DistBack#000008"},"Node 33":{"id":72,"t":"I","aF":"NONE","sprite":"Tower","feature":"X"},"Node 34":{"id":73,"t":"I","aF":"NONE","sprite":"Tower","feature":"Y"},"Node 35":{"id":74,"t":"I","aF":"NONE","sprite":"Tower","feature":"Dir"},"Node 36":{"id":75,"t":"I","aF":"NONE","sprite":"Tower","feature":"Size"},"Node 37":{"id":76,"t":"I","aF":"NONE","sprite":"Tower","feature":"Costume"},"Node 38":{"id":77,"t":"I","aF":"NONE","sprite":"Tower","feature":"DistCarX"},"Node 39":{"id":78,"t":"I","aF":"NONE","sprite":"Tower","feature":"DistCarY"},"Node 40":{"id":92,"t":"I","aF":"NONE","sprite":"Legs","feature":"X"},"Node 41":{"id":93,"t":"I","aF":"NONE","sprite":"Legs","feature":"Y"},"Node 42":{"id":94,"t":"I","aF":"NONE","sprite":"Legs","feature":"Dir"},"Node 43":{"id":95,"t":"I","aF":"NONE","sprite":"Legs","feature":"Size"},"Node 44":{"id":96,"t":"I","aF":"NONE","sprite":"Legs","feature":"DistCarX"},"Node 45":{"id":97,"t":"I","aF":"NONE","sprite":"Legs","feature":"DistCarY"},"Node 46":{"id":120,"t":"I","aF":"NONE","sprite":"Stage","feature":"Life"},"Node 47":{"id":130,"t":"I","aF":"NONE","sprite":"Car","feature":"DistRight#000008"},"Node 48":{"id":131,"t":"I","aF":"NONE","sprite":"Car","feature":"DistLeft#000008"},"Node 49":{"id":23,"t":"B","aF":"NONE"},"Node 50":{"id":32,"t":"H","aF":"TANH"},"Node 51":{"id":33,"t":"H","aF":"TANH"},"Node 52":{"id":34,"t":"H","aF":"TANH"},"Node 53":{"id":35,"t":"H","aF":"TANH"},"Node 54":{"id":36,"t":"H","aF":"TANH"},"Node 55":{"id":37,"t":"H","aF":"TANH"},"Node 56":{"id":38,"t":"H","aF":"TANH"},"Node 57":{"id":39,"t":"H","aF":"TANH"},"Node 58":{"id":24,"t":"C","aF":"NONE","event":"KeyPressEvent-right arrow"},"Node 59":{"id":25,"t":"C","aF":"NONE","event":"KeyPressEvent-left arrow"},"Node 60":{"id":26,"t":"C","aF":"NONE","event":"KeyPressEvent-up arrow"},"Node 61":{"id":27,"t":"C","aF":"NONE","event":"WaitEvent"},"Node 62":{"id":28,"t":"R","aF":"NONE","event":"KeyPressEvent-right arrow","eventP":"Steps"},"Node 63":{"id":29,"t":"R","aF":"NONE","event":"KeyPressEvent-left arrow","eventP":"Steps"},"Node 64":{"id":30,"t":"R","aF":"NONE","event":"KeyPressEvent-up arrow","eventP":"Steps"},"Node 65":{"id":31,"t":"R","aF":"NONE","event":"WaitEvent","eventP":"Duration"}},"Cons":{"Con 0":{"s":0,"t":32,"w":-0.48495,"e":true,"i":0,"r":false},"Con 1":{"s":32,"t":24,"w":-2.32944,"e":true,"i":1,"r":false},"Con 2":{"s":32,"t":25,"w":1.88387,"e":true,"i":2,"r":false},"Con 3":{"s":32,"t":26,"w":0.56259,"e":true,"i":3,"r":false},"Con 4":{"s":32,"t":27,"w":0.19954,"e":true,"i":4,"r":false},"Con 5":{"s":32,"t":28,"w":-0.45257,"e":true,"i":5,"r":false},"Con 6":{"s":32,"t":29,"w":-0.79551,"e":true,"i":6,"r":false},"Con 7":{"s":32,"t":30,"w":0.14426,"e":true,"i":7,"r":false},"Con 8":{"s":32,"t":31,"w":-1.72936,"e":true,"i":8,"r":false},"Con 9":{"s":1,"t":33,"w":0.7009,"e":true,"i":9,"r":false},"Con 10":{"s":2,"t":33,"w":-1.60956,"e":true,"i":10,"r":false},"Con 11":{"s":3,"t":33,"w":0.42836,"e":true,"i":11,"r":false},"Con 12":{"s":4,"t":33,"w":0.08179,"e":true,"i":12,"r":false},"Con 13":{"s":33,"t":24,"w":-0.57198,"e":true,"i":13,"r":false},"Con 14":{"s":33,"t":25,"w":-0.77986,"e":true,"i":14,"r":false},"Con 15":{"s":33,"t":26,"w":-1.22141,"e":true,"i":15,"r":false},"Con 16":{"s":33,"t":27,"w":-1.16641,"e":true,"i":16,"r":false},"Con 17":{"s":33,"t":28,"w":-1.23312,"e":true,"i":17,"r":false},"Con 18":{"s":33,"t":29,"w":1.24063,"e":true,"i":18,"r":false},"Con 19":{"s":33,"t":30,"w":-1.42029,"e":true,"i":19,"r":false},"Con 20":{"s":33,"t":31,"w":-0.96373,"e":true,"i":20,"r":false},"Con 21":{"s":5,"t":34,"w":0.50876,"e":true,"i":21,"r":false},"Con 22":{"s":6,"t":34,"w":-0.90236,"e":true,"i":22,"r":false},"Con 23":{"s":7,"t":34,"w":1.31424,"e":true,"i":23,"r":false},"Con 24":{"s":8,"t":34,"w":-1.05535,"e":true,"i":24,"r":false},"Con 25":{"s":34,"t":24,"w":-0.05553,"e":true,"i":25,"r":false},"Con 26":{"s":34,"t":25,"w":-1.26758,"e":true,"i":26,"r":false},"Con 27":{"s":34,"t":26,"w":2.02551,"e":true,"i":27,"r":false},"Con 28":{"s":34,"t":27,"w":-1.66505,"e":true,"i":28,"r":false},"Con 29":{"s":34,"t":28,"w":0.30865,"e":true,"i":29,"r":false},"Con 30":{"s":34,"t":29,"w":0.53528,"e":true,"i":30,"r":false},"Con 31":{"s":34,"t":30,"w":0.41239,"e":true,"i":31,"r":false},"Con 32":{"s":34,"t":31,"w":-0.69879,"e":true,"i":32,"r":false},"Con 33":{"s":9,"t":35,"w":-0.60954,"e":true,"i":33,"r":false},"Con 34":{"s":10,"t":35,"w":-1.29179,"e":true,"i":34,"r":false},"Con 35":{"s":11,"t":35,"w":-0.3047,"e":true,"i":35,"r":false},"Con 36":{"s":12,"t":35,"w":0.15792,"e":true,"i":36,"r":false},"Con 37":{"s":13,"t":35,"w":0.9716,"e":true,"i":37,"r":false},"Con 38":{"s":35,"t":24,"w":0.92137,"e":true,"i":38,"r":false},"Con 39":{"s":35,"t":25,"w":0.39369,"e":true,"i":39,"r":false},"Con 40":{"s":35,"t":26,"w":-0.91836,"e":true,"i":40,"r":false},"Con 41":{"s":35,"t":27,"w":1.59782,"e":true,"i":41,"r":false},"Con 42":{"s":35,"t":28,"w":-0.33647,"e":true,"i":42,"r":false},"Con 43":{"s":35,"t":29,"w":-0.54032,"e":true,"i":43,"r":false},"Con 44":{"s":35,"t":30,"w":0.65906,"e":true,"i":44,"r":false},"Con 45":{"s":35,"t":31,"w":0.26483,"e":true,"i":45,"r":false},"Con 46":{"s":14,"t":36,"w":-0.06893,"e":true,"i":46,"r":false},"Con 47":{"s":15,"t":36,"w":-0.17638,"e":true,"i":47,"r":false},"Con 48":{"s":16,"t":36,"w":0.98526,"e":true,"i":48,"r":false},"Con 49":{"s":36,"t":24,"w":1.28238,"e":true,"i":49,"r":false},"Con 50":{"s":36,"t":25,"w":-1.89669,"e":true,"i":50,"r":false},"Con 51":{"s":36,"t":26,"w":0.65085,"e":true,"i":51,"r":false},"Con 52":{"s":36,"t":27,"w":-1.43174,"e":true,"i":52,"r":false},"Con 53":{"s":36,"t":28,"w":0.31281,"e":true,"i":53,"r":false},"Con 54":{"s":36,"t":29,"w":-0.95772,"e":true,"i":54,"r":false},"Con 55":{"s":36,"t":30,"w":0.68131,"e":true,"i":55,"r":false},"Con 56":{"s":36,"t":31,"w":0.54798,"e":true,"i":56,"r":false},"Con 57":{"s":17,"t":37,"w":-0.5805,"e":true,"i":57,"r":false},"Con 58":{"s":18,"t":37,"w":0.53587,"e":true,"i":58,"r":false},"Con 59":{"s":19,"t":37,"w":0.09184,"e":true,"i":59,"r":false},"Con 60":{"s":37,"t":24,"w":1.88425,"e":true,"i":60,"r":false},"Con 61":{"s":37,"t":25,"w":1.40457,"e":true,"i":61,"r":false},"Con 62":{"s":37,"t":26,"w":-0.61466,"e":true,"i":62,"r":false},"Con 63":{"s":37,"t":27,"w":-0.29889,"e":true,"i":63,"r":false},"Con 64":{"s":37,"t":28,"w":0.73116,"e":true,"i":64,"r":false},"Con 65":{"s":37,"t":29,"w":1.76153,"e":true,"i":65,"r":false},"Con 66":{"s":37,"t":30,"w":-1.63262,"e":true,"i":66,"r":false},"Con 67":{"s":37,"t":31,"w":1.74013,"e":true,"i":67,"r":false},"Con 68":{"s":20,"t":38,"w":0.5754,"e":true,"i":68,"r":false},"Con 69":{"s":21,"t":38,"w":-0.5913,"e":true,"i":69,"r":false},"Con 70":{"s":22,"t":38,"w":0.05771,"e":true,"i":70,"r":false},"Con 71":{"s":38,"t":24,"w":0.56617,"e":true,"i":71,"r":false},"Con 72":{"s":38,"t":25,"w":-1.31081,"e":true,"i":72,"r":false},"Con 73":{"s":38,"t":26,"w":-1.04364,"e":true,"i":73,"r":false},"Con 74":{"s":38,"t":27,"w":0.19114,"e":true,"i":74,"r":false},"Con 75":{"s":38,"t":28,"w":0.67988,"e":true,"i":75,"r":false},"Con 76":{"s":38,"t":29,"w":-0.37387,"e":true,"i":76,"r":false},"Con 77":{"s":38,"t":30,"w":1.24065,"e":true,"i":77,"r":false},"Con 78":{"s":38,"t":31,"w":-1.13751,"e":true,"i":78,"r":false},"Con 79":{"s":23,"t":39,"w":0.78331,"e":true,"i":79,"r":false},"Con 80":{"s":39,"t":24,"w":-0.256,"e":true,"i":80,"r":false},"Con 81":{"s":39,"t":25,"w":-0.35775,"e":true,"i":81,"r":false},"Con 82":{"s":39,"t":26,"w":1.30479,"e":true,"i":82,"r":false},"Con 83":{"s":39,"t":27,"w":-0.29365,"e":true,"i":83,"r":false},"Con 84":{"s":39,"t":28,"w":-0.6247,"e":true,"i":84,"r":false},"Con 85":{"s":39,"t":29,"w":-1.02654,"e":true,"i":85,"r":false},"Con 86":{"s":39,"t":30,"w":-0.59341,"e":true,"i":86,"r":false},"Con 87":{"s":39,"t":31,"w":0.20904,"e":true,"i":87,"r":false}}},"Network 8":{"id":3921,"aF":"TANH","cM":"fullyHidden","tf":"mlK^#^TSH~VCSPIQ=bQN-Car","Nodes":{"Node 0":{"id":0,"t":"I","aF":"NONE","sprite":"Stage","feature":"Scroll"},"Node 1":{"id":1,"t":"I","aF":"NONE","sprite":"Road1","feature":"X"},"Node 2":{"id":2,"t":"I","aF":"NONE","sprite":"Road1","feature":"Y"},"Node 3":{"id":3,"t":"I","aF":"NONE","sprite":"Road1","feature":"Dir"},"Node 4":{"id":4,"t":"I","aF":"NONE","sprite":"Road1","feature":"Size"},"Node 5":{"id":5,"t":"I","aF":"NONE","sprite":"Road2","feature":"X"},"Node 6":{"id":6,"t":"I","aF":"NONE","sprite":"Road2","feature":"Y"},"Node 7":{"id":7,"t":"I","aF":"NONE","sprite":"Road2","feature":"Dir"},"Node 8":{"id":8,"t":"I","aF":"NONE","sprite":"Road2","feature":"Size"},"Node 9":{"id":9,"t":"I","aF":"NONE","sprite":"Car","feature":"X"},"Node 10":{"id":10,"t":"I","aF":"NONE","sprite":"Car","feature":"Y"},"Node 11":{"id":11,"t":"I","aF":"NONE","sprite":"Car","feature":"Dir"},"Node 12":{"id":12,"t":"I","aF":"NONE","sprite":"Car","feature":"Size"},"Node 13":{"id":13,"t":"I","aF":"NONE","sprite":"Car","feature":"Costume"},"Node 14":{"id":14,"t":"I","aF":"NONE","sprite":"Gobo","feature":"X"},"Node 15":{"id":15,"t":"I","aF":"NONE","sprite":"Gobo","feature":"Y"},"Node 16":{"id":16,"t":"I","aF":"NONE","sprite":"Gobo","feature":"Size"},"Node 17":{"id":17,"t":"I","aF":"NONE","sprite":"Fabu","feature":"X"},"Node 18":{"id":18,"t":"I","aF":"NONE","sprite":"Fabu","feature":"Y"},"Node 19":{"id":19,"t":"I","aF":"NONE","sprite":"Fabu","feature":"Size"},"Node 20":{"id":20,"t":"I","aF":"NONE","sprite":"Pele","feature":"X"},"Node 21":{"id":21,"t":"I","aF":"NONE","sprite":"Pele","feature":"Y"},"Node 22":{"id":22,"t":"I","aF":"NONE","sprite":"Pele","feature":"Size"},"Node 23":{"id":62,"t":"I","aF":"NONE","sprite":"Stage","feature":"Time"},"Node 24":{"id":70,"t":"I","aF":"NONE","sprite":"Car","feature":"DistFront#000008"},"Node 25":{"id":130,"t":"I","aF":"NONE","sprite":"Car","feature":"DistRight#000008"},"Node 26":{"id":23,"t":"B","aF":"NONE"},"Node 27":{"id":32,"t":"H","aF":"TANH"},"Node 28":{"id":33,"t":"H","aF":"TANH"},"Node 29":{"id":34,"t":"H","aF":"TANH"},"Node 30":{"id":35,"t":"H","aF":"TANH"},"Node 31":{"id":36,"t":"H","aF":"TANH"},"Node 32":{"id":37,"t":"H","aF":"TANH"},"Node 33":{"id":38,"t":"H","aF":"TANH"},"Node 34":{"id":39,"t":"H","aF":"TANH"},"Node 35":{"id":24,"t":"C","aF":"NONE","event":"KeyPressEvent-right arrow"},"Node 36":{"id":25,"t":"C","aF":"NONE","event":"KeyPressEvent-left arrow"},"Node 37":{"id":26,"t":"C","aF":"NONE","event":"KeyPressEvent-up arrow"},"Node 38":{"id":27,"t":"C","aF":"NONE","event":"WaitEvent"},"Node 39":{"id":28,"t":"R","aF":"NONE","event":"KeyPressEvent-right arrow","eventP":"Steps"},"Node 40":{"id":29,"t":"R","aF":"NONE","event":"KeyPressEvent-left arrow","eventP":"Steps"},"Node 41":{"id":30,"t":"R","aF":"NONE","event":"KeyPressEvent-up arrow","eventP":"Steps"},"Node 42":{"id":31,"t":"R","aF":"NONE","event":"WaitEvent","eventP":"Duration"}},"Cons":{"Con 0":{"s":0,"t":32,"w":1.12485,"e":true,"i":0,"r":false},"Con 1":{"s":32,"t":24,"w":-1.3562,"e":true,"i":1,"r":false},"Con 2":{"s":32,"t":25,"w":0.43444,"e":true,"i":2,"r":false},"Con 3":{"s":32,"t":26,"w":-0.51834,"e":true,"i":3,"r":false},"Con 4":{"s":32,"t":27,"w":1.48221,"e":true,"i":4,"r":false},"Con 5":{"s":32,"t":28,"w":-0.29234,"e":true,"i":5,"r":false},"Con 6":{"s":32,"t":29,"w":0.57231,"e":true,"i":6,"r":false},"Con 7":{"s":32,"t":30,"w":-0.46996,"e":true,"i":7,"r":false},"Con 8":{"s":32,"t":31,"w":0.13581,"e":true,"i":8,"r":false},"Con 9":{"s":1,"t":33,"w":0.69114,"e":true,"i":9,"r":false},"Con 10":{"s":2,"t":33,"w":2.84158,"e":true,"i":10,"r":false},"Con 11":{"s":3,"t":33,"w":-0.48837,"e":true,"i":11,"r":false},"Con 12":{"s":4,"t":33,"w":-1.2168,"e":true,"i":12,"r":false},"Con 13":{"s":33,"t":24,"w":-0.2117,"e":true,"i":13,"r":false},"Con 14":{"s":33,"t":25,"w":-1.57591,"e":true,"i":14,"r":false},"Con 15":{"s":33,"t":26,"w":0.93976,"e":true,"i":15,"r":false},"Con 16":{"s":33,"t":27,"w":0.41248,"e":true,"i":16,"r":false},"Con 17":{"s":33,"t":28,"w":1.00723,"e":true,"i":17,"r":false},"Con 18":{"s":33,"t":29,"w":0.30402,"e":true,"i":18,"r":false},"Con 19":{"s":33,"t":30,"w":0.25867,"e":true,"i":19,"r":false},"Con 20":{"s":33,"t":31,"w":-0.89312,"e":true,"i":20,"r":false},"Con 21":{"s":5,"t":34,"w":-1.02446,"e":true,"i":21,"r":false},"Con 22":{"s":6,"t":34,"w":1.37804,"e":true,"i":22,"r":false},"Con 23":{"s":7,"t":34,"w":-0.74062,"e":true,"i":23,"r":false},"Con 24":{"s":8,"t":34,"w":-0.21633,"e":true,"i":24,"r":false},"Con 25":{"s":34,"t":24,"w":-0.28543,"e":true,"i":25,"r":false},"Con 26":{"s":34,"t":25,"w":0.0697,"e":true,"i":26,"r":false},"Con 27":{"s":34,"t":26,"w":-1.66494,"e":true,"i":27,"r":false},"Con 28":{"s":34,"t":27,"w":0.39166,"e":true,"i":28,"r":false},"Con 29":{"s":34,"t":28,"w":-0.53322,"e":true,"i":29,"r":false},"Con 30":{"s":34,"t":29,"w":-1.18157,"e":true,"i":30,"r":false},"Con 31":{"s":34,"t":30,"w":-1.15463,"e":true,"i":31,"r":false},"Con 32":{"s":34,"t":31,"w":-0.79154,"e":true,"i":32,"r":false},"Con 33":{"s":9,"t":35,"w":0.20053,"e":true,"i":33,"r":false},"Con 34":{"s":10,"t":35,"w":-2.11253,"e":true,"i":34,"r":false},"Con 35":{"s":11,"t":35,"w":-0.24609,"e":true,"i":35,"r":false},"Con 36":{"s":12,"t":35,"w":-1.25516,"e":true,"i":36,"r":false},"Con 37":{"s":13,"t":35,"w":-0.55063,"e":true,"i":37,"r":false},"Con 38":{"s":35,"t":24,"w":0.82604,"e":true,"i":38,"r":false},"Con 39":{"s":35,"t":25,"w":-1.72118,"e":true,"i":39,"r":false},"Con 40":{"s":35,"t":26,"w":-0.06571,"e":true,"i":40,"r":false},"Con 41":{"s":35,"t":27,"w":-0.84838,"e":true,"i":41,"r":false},"Con 42":{"s":35,"t":28,"w":1.55324,"e":true,"i":42,"r":false},"Con 43":{"s":35,"t":29,"w":-0.21316,"e":true,"i":43,"r":false},"Con 44":{"s":35,"t":30,"w":0.917,"e":true,"i":44,"r":false},"Con 45":{"s":35,"t":31,"w":-0.55653,"e":true,"i":45,"r":false},"Con 46":{"s":14,"t":36,"w":-1.73309,"e":true,"i":46,"r":false},"Con 47":{"s":15,"t":36,"w":1.05861,"e":true,"i":47,"r":false},"Con 48":{"s":16,"t":36,"w":-0.2771,"e":true,"i":48,"r":false},"Con 49":{"s":36,"t":24,"w":0.54812,"e":true,"i":49,"r":false},"Con 50":{"s":36,"t":25,"w":-1.44513,"e":true,"i":50,"r":false},"Con 51":{"s":36,"t":26,"w":0.56498,"e":true,"i":51,"r":false},"Con 52":{"s":36,"t":27,"w":-1.19257,"e":true,"i":52,"r":false},"Con 53":{"s":36,"t":28,"w":-0.50228,"e":true,"i":53,"r":false},"Con 54":{"s":36,"t":29,"w":0.41474,"e":true,"i":54,"r":false},"Con 55":{"s":36,"t":30,"w":-2.27429,"e":true,"i":55,"r":false},"Con 56":{"s":36,"t":31,"w":1.54368,"e":true,"i":56,"r":false},"Con 57":{"s":17,"t":37,"w":-0.53043,"e":true,"i":57,"r":false},"Con 58":{"s":18,"t":37,"w":-0.77483,"e":true,"i":58,"r":false},"Con 59":{"s":19,"t":37,"w":0.65553,"e":true,"i":59,"r":false},"Con 60":{"s":37,"t":24,"w":-0.14923,"e":true,"i":60,"r":false},"Con 61":{"s":37,"t":25,"w":-0.48923,"e":true,"i":61,"r":false},"Con 62":{"s":37,"t":26,"w":-1.17047,"e":true,"i":62,"r":false},"Con 63":{"s":37,"t":27,"w":0.34554,"e":true,"i":63,"r":false},"Con 64":{"s":37,"t":28,"w":0.89174,"e":true,"i":64,"r":false},"Con 65":{"s":37,"t":29,"w":1.09982,"e":true,"i":65,"r":false},"Con 66":{"s":37,"t":30,"w":0.04415,"e":true,"i":66,"r":false},"Con 67":{"s":37,"t":31,"w":1.69859,"e":true,"i":67,"r":false},"Con 68":{"s":20,"t":38,"w":0.42307,"e":true,"i":68,"r":false},"Con 69":{"s":21,"t":38,"w":0.27409,"e":true,"i":69,"r":false},"Con 70":{"s":22,"t":38,"w":-1.90881,"e":true,"i":70,"r":false},"Con 71":{"s":38,"t":24,"w":0.47735,"e":true,"i":71,"r":false},"Con 72":{"s":38,"t":25,"w":0.44626,"e":true,"i":72,"r":false},"Con 73":{"s":38,"t":26,"w":1.59075,"e":true,"i":73,"r":false},"Con 74":{"s":38,"t":27,"w":-1.73505,"e":true,"i":74,"r":false},"Con 75":{"s":38,"t":28,"w":-0.92618,"e":true,"i":75,"r":false},"Con 76":{"s":38,"t":29,"w":0.88074,"e":true,"i":76,"r":false},"Con 77":{"s":38,"t":30,"w":0.87893,"e":true,"i":77,"r":false},"Con 78":{"s":38,"t":31,"w":0.46378,"e":true,"i":78,"r":false},"Con 79":{"s":23,"t":39,"w":-0.3479,"e":true,"i":79,"r":false},"Con 80":{"s":39,"t":24,"w":0.12925,"e":true,"i":80,"r":false},"Con 81":{"s":39,"t":25,"w":0.20663,"e":true,"i":81,"r":false},"Con 82":{"s":39,"t":26,"w":-0.0385,"e":true,"i":82,"r":false},"Con 83":{"s":39,"t":27,"w":-0.59563,"e":true,"i":83,"r":false},"Con 84":{"s":39,"t":28,"w":0.8665,"e":true,"i":84,"r":false},"Con 85":{"s":39,"t":29,"w":-2.25656,"e":true,"i":85,"r":false},"Con 86":{"s":39,"t":30,"w":0.17164,"e":true,"i":86,"r":false},"Con 87":{"s":39,"t":31,"w":0.71037,"e":true,"i":87,"r":false}}}}}