{"Configs":{"testSuiteType":"dynamic","timeout":10000,"eventSelection":"activation","seed":7,"durations":{"waitStepUpperBound":50,"pressDurationUpperBound":10,"soundDuration":10,"clickDuration":10}},"Networks":{"Network 0":{"id":0,"aF":"TANH","cM":"fullyHidden","tf":"fWPh!(5%}~n%X3q.fnq1-Snowball","Nodes":{"Node 0":{"id":0,"t":"I","aF":"NONE","sprite":"Stage","feature":"power"},"Node 1":{"id":1,"t":"I","aF":"NONE","sprite":"Snowball","feature":"X"},"Node 2":{"id":2,"t":"I","aF":"NONE","sprite":"Snowball","feature":"Y"},"Node 3":{"id":3,"t":"I","aF":"NONE","sprite":"Snowball","feature":"Dir"},"Node 4":{"id":4,"t":"I","aF":"NONE","sprite":"Snowball","feature":"Size"},"Node 5":{"id":5,"t":"I","aF":"NONE","sprite":"Snowball","feature":"Costume"},"Node 6":{"id":6,"t":"I","aF":"NONE","sprite":"Snowball","feature":"DistRocksX"},"Node 7":{"id":7,"t":"I","aF":"NONE","sprite":"Snowball","feature":"DistRocksY"},"Node 8":{"id":8,"t":"I","aF":"NONE","sprite":"Bear","feature":"X"},"Node 9":{"id":9,"t":"I","aF":"NONE","sprite":"Bear","feature":"Y"},"Node 10":{"id":10,"t":"I","aF":"NONE","sprite":"Bear","feature":"Dir"},"Node 11":{"id":11,"t":"I","aF":"NONE","sprite":"Bear","feature":"Size"},"Node 12":{"id":12,"t":"I","aF":"NONE","sprite":"Bear","feature":"DistSnowballX"},"Node 13":{"id":13,"t":"I","aF":"NONE","sprite":"Bear","feature":"DistSnowballY"},"Node 14":{"id":14,"t":"I","aF":"NONE","sprite":"Rocks","feature":"X"},"Node 15":{"id":15,"t":"I","aF":"NONE","sprite":"Rocks","feature":"Y"},"Node 16":{"id":16,"t":"I","aF":"NONE","sprite":"Rocks","feature":"Dir"},"Node 17":{"id":17,"t":"I","aF":"NONE","sprite":"Rocks","feature":"Size"},"Node 18":{"id":18,"t":"I","aF":"NONE","sprite":"Rocks","feature":"DistBearX"},"Node 19":{"id":19,"t":"I","aF":"NONE","sprite":"Rocks","feature":"DistBearY"},"Node 20":{"id":20,"t":"B","aF":"NONE"},"Node 21":{"id":28,"t":"H","aF":"TANH"},"Node 22":{"id":29,"t":"H","aF":"TANH"},"Node 23":{"id":30,"t":"H","aF":"TANH"},"Node 24":{"id":31,"t":"H","aF":"TANH"},"Node 25":{"id":32,"t":"H","aF":"TANH"},"Node 26":{"id":21,"t":"C","aF":"NONE","event":"MouseMoveEvent"},"Node 27":{"id":22,"t":"C","aF":"NONE","event":"KeyPressEvent-space"},"Node 28":{"id":23,"t":"C","aF":"NONE","event":"WaitEvent"},"Node 29":{"id":24,"t":"R","aF":"NONE","event":"MouseMoveEvent","eventP":"X"},"Node 30":{"id":25,"t":"R","aF":"NONE","event":"MouseMoveEvent","eventP":"Y"},"Node 31":{"id":26,"t":"R","aF":"NONE","event":"KeyPressEvent-space","eventP":"Steps"},"Node 32":{"id":27,"t":"R","aF":"NONE","event":"WaitEvent","eventP":"Duration"}},"Cons":{"Con 0":{"s":0,"t":28,"w":1.00106,"e":true,"i":0,"r":false},"Con 1":{"s":28,"t":21,"w":0.11208,"e":true,"i":1,"r":false},"Con 2":{"s":28,"t":22,"w":-1.5922,"e":true,"i":2,"r":false},"Con 3":{"s":28,"t":23,"w":-1.12503,"e":true,"i":3,"r":false},"Con 4":{"s":28,"t":24,"w":0.25445,"e":true,"i":4,"r":false},"Con 5":{"s":28,"t":25,"w":0.34314,"e":true,"i":5,"r":false},"Con 6":{"s":28,"t":26,"w":-0.49538,"e":true,"i":6,"r":false},"Con 7":{"s":28,"t":27,"w":1.31121,"e":true,"i":7,"r":false},"Con 8":{"s":1,"t":29,"w":0.85577,"e":true,"i":8,"r":false},"Con 9":{"s":2,"t":29,"w":1.21586,"e":true,"i":9,"r":false},"Con 10":{"s":3,"t":29,"w":-2.37894,"e":true,"i":10,"r":false},"Con 11":{"s":4,"t":29,"w":-0.46959,"e":true,"i":11,"r":false},"Con 12":{"s":5,"t":29,"w":-0.76622,"e":true,"i":12,"r":false},"Con 13":{"s":6,"t":29,"w":-1.31642,"e":true,"i":13,"r":false},"Con 14":{"s":7,"t":29,"w":0.55571,"e":true,"i":14,"r":false},"Con 15":{"s":29,"t":21,"w":-0.45385,"e":true,"i":15,"r":false},"Con 16":{"s":29,"t":22,"w":0.32653,"e":true,"i":16,"r":false},"Con 17":{"s":29,"t":23,"w":1.90743,"e":true,"i":17,"r":false},"Con 18":{"s":29,"t":24,"w":-1.26092,"e":true,"i":18,"r":false},"Con 19":{"s":29,"t":25,"w":-1.93548,"e":true,"i":19,"r":false},"Con 20":{"s":29,"t":26,"w":0.38672,"e":true,"i":20,"r":false},"Con 21":{"s":29,"t":27,"w":0.07181,"e":true,"i":21,"r":false},"Con 22":{"s":8,"t":30,"w":0.80303,"e":true,"i":22,"r":false},"Con 23":{"s":9,"t":30,"w":-0.81659,"e":true,"i":23,"r":false},"Con 24":{"s":10,"t":30,"w":0.87282,"e":true,"i":24,"r":false},"Con 25":{"s":11,"t":30,"w":0.73949,"e":true,"i":25,"r":false},"Con 26":{"s":12,"t":30,"w":0.62154,"e":true,"i":26,"r":false},"Con 27":{"s":13,"t":30,"w":-0.98001,"e":true,"i":27,"r":false},"Con 28":{"s":30,"t":21,"w":0.38709,"e":true,"i":28,"r":false},"Con 29":{"s":30,"t":22,"w":-2.17247,"e":true,"i":29,"r":false},"Con 30":{"s":30,"t":23,"w":-0.19301,"e":true,"i":30,"r":false},"Con 31":{"s":30,"t":24,"w":-1.7591,"e":true,"i":31,"r":false},"Con 32":{"s":30,"t":25,"w":1.05384,"e":true,"i":32,"r":false},"Con 33":{"s":30,"t":26,"w":1.54502,"e":true,"i":33,"r":false},"Con 34":{"s":30,"t":27,"w":0.74121,"e":true,"i":34,"r":false},"Con 35":{"s":14,"t":31,"w":1.5364,"e":true,"i":35,"r":false},"Con 36":{"s":15,"t":31,"w":-0.22588,"e":true,"i":36,"r":false},"Con 37":{"s":16,"t":31,"w":1.01105,"e":true,"i":37,"r":false},"Con 38":{"s":17,"t":31,"w":0.38565,"e":true,"i":38,"r":false},"Con 39":{"s":18,"t":31,"w":0.84789,"e":true,"i":39,"r":false},"Con 40":{"s":19,"t":31,"w":-1.57924,"e":true,"i":40,"r":false},"Con 41":{"s":31,"t":21,"w":-1.38683,"e":true,"i":41,"r":false},"Con 42":{"s":31,"t":22,"w":0.53486,"e":true,"i":42,"r":false},"Con 43":{"s":31,"t":23,"w":-0.51955,"e":true,"i":43,"r":false},"Con 44":{"s":31,"t":24,"w":-0.65257,"e":true,"i":44,"r":false},"Con 45":{"s":31,"t":25,"w":-1.24729,"e":true,"i":45,"r":false},"Con 46":{"s":31,"t":26,"w":1.29978,"e":true,"i":46,"r":false},"Con 47":{"s":31,"t":27,"w":-0.93282,"e":true,"i":47,"r":false},"Con 48":{"s":20,"t":32,"w":0.36542,"e":true,"i":48,"r":false},"Con 49":{"s":32,"t":21,"w":-0.8774,"e":true,"i":49,"r":false},"Con 50":{"s":32,"t":22,"w":1.65746,"e":true,"i":50,"r":false},"Con 51":{"s":32,"t":23,"w":0.27955,"e":true,"i":51,"r":false},"Con 52":{"s":32,"t":24,"w":0.42966,"e":true,"i":52,"r":false},"Con 53":{"s":32,"t":25,"w":0.59197,"e":true,"i":53,"r":false},"Con 54":{"s":32,"t":26,"w":-0.3704,"e":true,"i":54,"r":false},"Con 55":{"s":32,"t":27,"w":0.44651,"e":true,"i":55,"r":false}}},"Network 1":{"id":602,"aF":"TANH","cM":"fullyHidden","tf":"s=-(}/LnXItzVdA}3fu|-Snowball","Nodes":{"Node 0":{"id":0,"t":"I","aF":"NONE","sprite":"Stage","feature":"power"},"Node 1":{"id":1,"t":"I","aF":"NONE","sprite":"Snowball","feature":"X"},"Node 2":{"id":2,"t":"I","aF":"NONE","sprite":"Snowball","feature":"Y"},"Node 3":{"id":3,"t":"I","aF":"NONE","sprite":"Snowball","feature":"Dir"},"Node 4":{"id":4,"t":"I","aF":"NONE","sprite":"Snowball","feature":"Size"},"Node 5":{"id":5,"t":"I","aF":"NONE","sprite":"Snowball","feature":"Costume"},"Node 6":{"id":6,"t":"I","aF":"NONE","sprite":"Snowball","feature":"DistRocksX"},"Node 7":{"id":7,"t":"I","aF":"NONE","sprite":"Snowball","feature":"DistRocksY"},"Node 8":{"id":8,"t":"I","aF":"NONE","sprite":"Bear","feature":"X"},"Node 9":{"id":9,"t":"I","aF":"NONE","sprite":"Bear","feature":"Y"},"Node 10":{"id":10,"t":"I","aF":"NONE","sprite":"Bear","feature":"Dir"},"Node 11":{"id":11,"t":"I","aF":"NONE","sprite":"Bear","feature":"Size"},"Node 12":{"id":12,"t":"I","aF":"NONE","sprite":"Bear","feature":"DistSnowballX"},"Node 13":{"id":13,"t":"I","aF":"NONE","sprite":"Bear","feature":"DistSnowballY"},"Node 14":{"id":14,"t":"I","aF":"NONE","sprite":"Rocks","feature":"X"},"Node 15":{"id":15,"t":"I","aF":"NONE","sprite":"Rocks","feature":"Y"},"Node 16":{"id":16,"t":"I","aF":"NONE","sprite":"Rocks","feature":"Dir"},"Node 17":{"id":17,"t":"I","aF":"NONE","sprite":"Rocks","feature":"Size"},"Node 18":{"id":18,"t":"I","aF":"NONE","sprite":"Rocks","feature":"DistBearX"},"Node 19":{"id":19,"t":"I","aF":"NONE","sprite":"Rocks","feature":"DistBearY"},"Node 20":{"id":20,"t":"B","aF":"NONE"},"Node 21":{"id":28,"t":"H","aF":"TANH"},"Node 22":{"id":29,"t":"H","aF":"TANH"},"Node 23":{"id":30,"t":"H","aF":"TANH"},"Node 24":{"id":31,"t":"H","aF":"TANH"},"Node 25":{"id":32,"t":"H","aF":"TANH"},"Node 26":{"id":21,"t":"C","aF":"NONE","event":"MouseMoveEvent"},"Node 27":{"id":22,"t":"C","aF":"NONE","event":"KeyPressEvent-space"},"Node 28":{"id":23,"t":"C","aF":"NONE","event":"WaitEvent"},"Node 29":{"id":24,"t":"R","aF":"NONE","event":"MouseMoveEvent","eventP":"X"},"Node 30":{"id":25,"t":"R","aF":"NONE","event":"MouseMoveEvent","eventP":"Y"},"Node 31":{"id":26,"t":"R","aF":"NONE","event":"KeyPressEvent-space","eventP":"Steps"},"Node 32":{"id":27,"t":"R","aF":"NONE","event":"WaitEvent","eventP":"Duration"}},"Cons":{"Con 0":{"s":0,"t":28,"w":-0.98404,"e":true,"i":0,"r":false},"Con 1":{"s":28,"t":21,"w":-0.41893,"e":true,"i":1,"r":false},"Con 2":{"s":28,"t":22,"w":0.34094,"e":true,"i":2,"r":false},"Con 3":{"s":28,"t":23,"w":-1.09045,"e":true,"i":3,"r":false},"Con 4":{"s":28,"t":24,"w":0.70567,"e":true,"i":4,"r":false},"Con 5":{"s":28,"t":25,"w":-0.3411,"e":true,"i":5,"r":false},"Con 6":{"s":28,"t":26,"w":-0.63771,"e":true,"i":6,"r":false},"Con 7":{"s":28,"t":27,"w":0.41063,"e":true,"i":7,"r":false},"Con 8":{"s":1,"t":29,"w":0.83996,"e":true,"i":8,"r":false},"Con 9":{"s":2,"t":29,"w":-1.25776,"e":true,"i":9,"r":false},"Con 10":{"s":3,"t":29,"w":-1.86833,"e":true,"i":10,"r":false},"Con 11":{"s":4,"t":29,"w":-0.31505,"e":true,"i":11,"r":false},"Con 12":{"s":5,"t":29,"w":1.30709,"e":true,"i":12,"r":false},"Con 13":{"s":6,"t":29,"w":-0.72472,"e":true,"i":13,"r":false},"Con 14":{"s":7,"t":29,"w":0.15573,"e":true,"i":14,"r":false},"Con 15":{"s":29,"t":21,"w":1.27686,"e":true,"i":15,"r":false},"Con 16":{"s":29,"t":22,"w":0.17653,"e":true,"i":16,"r":false},"Con 17":{"s":29,"t":23,"w":1.11612,"e":true,"i":17,"r":false},"Con 18":{"s":29,"t":24,"w":1.77256,"e":true,"i":18,"r":false},"Con 19":{"s":29,"t":25,"w":-0.5341,"e":true,"i":19,"r":false},"Con 20":{"s":29,"t":26,"w":0.6334,"e":true,"i":20,"r":false},"Con 21":{"s":29,"t":27,"w":-0.03334,"e":true,"i":21,"r":false},"Con 22":{"s":8,"t":30,"w":0.18054,"e":true,"i":22,"r":false},"Con 23":{"s":9,"t":30,"w":0.94912,"e":true,"i":23,"r":false},"Con 24":{"s":10,"t":30,"w":-0.05952,"e":true,"i":24,"r":false},"Con 25":{"s":11,"t":30,"w":-0.5022,"e":true,"i":25,"r":false},"Con 26":{"s":12,"t":30,"w":0.46995,"e":true,"i":26,"r":false},"Con 27":{"s":13,"t":30,"w":-0.34217,"e":true,"i":27,"r":false},"Con 28":{"s":30,"t":21,"w":2.08652,"e":true,"i":28,"r":false},"Con 29":{"s":30,"t":22,"w":0.58485,"e":true,"i":29,"r":false},"Con 30":{"s":30,"t":23,"w":-0.88091,"e":true,"i":30,"r":false},"Con 31":{"s":30,"t":24,"w":2.44587,"e":true,"i":31,"r":false},"Con 32":{"s":30,"t":25,"w":0.00461,"e":true,"i":32,"r":false},"Con 33":{"s":30,"t":26,"w":-0.12677,"e":true,"i":33,"r":false},"Con 34":{"s":30,"t":27,"w":0.63707,"e":true,"i":34,"r":false},"Con 35":{"s":14,"t":31,"w":-1.37525,"e":true,"i":35,"r":false},"Con 36":{"s":15,"t":31,"w":-0.13389,"e":true,"i":36,"r":false},"Con 37":{"s":16,"t":31,"w":0.61726,"e":true,"i":37,"r":false},"Con 38":{"s":17,"t":31,"w":-0.76741,"e":true,"i":38,"r":false},"Con 39":{"s":18,"t":31,"w":-0.45734,"e":true,"i":39,"r":false},"Con 40":{"s":19,"t":31,"w":-0.77403,"e":true,"i":40,"r":false},"Con 41":{"s":31,"t":21,"w":1.50356,"e":true,"i":41,"r":false},"Con 42":{"s":31,"t":22,"w":0.63137,"e":true,"i":42,"r":false},"Con 43":{"s":31,"t":23,"w":-0.0758,"e":true,"i":43,"r":false},"Con 44":{"s":31,"t":24,"w":-1.82867,"e":true,"i":44,"r":false},"Con 45":{"s":31,"t":25,"w":0.32466,"e":true,"i":45,"r":false},"Con 46":{"s":31,"t":26,"w":-0.51514,"e":true,"i":46,"r":false},"Con 47":{"s":31,"t":27,"w":0.18753,"e":true,"i":47,"r":false},"Con 48":{"s":20,"t":32,"w":-0.68519,"e":true,"i":48,"r":false},"Con 49":{"s":32,"t":21,"w":0.30603,"e":true,"i":49,"r":false},"Con 50":{"s":32,"t":22,"w":0.63609,"e":true,"i":50,"r":false},"Con 51":{"s":32,"t":23,"w":0.28174,"e":true,"i":51,"r":false},"Con 52":{"s":32,"t":24,"w":2.39456,"e":true,"i":52,"r":false},"Con 53":{"s":32,"t":25,"w":-1.29163,"e":true,"i":53,"r":false},"Con 54":{"s":32,"t":26,"w":-0.32395,"e":true,"i":54,"r":false},"Con 55":{"s":32,"t":27,"w":0.223,"e":true,"i":55,"r":false}}},"Network 2":{"id":11978,"aF":"TANH","cM":"fullyHidden","tf":")X{a/zeNv|(*:hM?IkHX-Bear","Nodes":{"Node 0":{"id":0,"t":"I","aF":"NONE","sprite":"Stage","feature":"power"},"Node 1":{"id":1,"t":"I","aF":"NONE","sprite":"Snowball","feature":"X"},"Node 2":{"id":2,"t":"I","aF":"NONE","sprite":"Snowball","feature":"Y"},"Node 3":{"id":3,"t":"I","aF":"NONE","sprite":"Snowball","feature":"Dir"},"Node 4":{"id":4,"t":"I","aF":"NONE","sprite":"Snowball","feature":"Size"},"Node 5":{"id":5,"t":"I","aF":"NONE","sprite":"Snowball","feature":"Costume"},"Node 6":{"id":6,"t":"I","aF":"NONE","sprite":"Snowball","feature":"DistRocksX"},"Node 7":{"id":7,"t":"I","aF":"NONE","sprite":"Snowball","feature":"DistRocksY"},"Node 8":{"id":8,"t":"I","aF":"NONE","sprite":"Bear","feature":"X"},"Node 9":{"id":9,"t":"I","aF":"NONE","sprite":"Bear","feature":"Y"},"Node 10":{"id":10,"t":"I","aF":"NONE","sprite":"Bear","feature":"Dir"},"Node 11":{"id":11,"t":"I","aF":"NONE","sprite":"Bear","feature":"Size"},"Node 12":{"id":12,"t":"I","aF":"NONE","sprite":"Bear","feature":"DistSnowballX"},"Node 13":{"id":13,"t":"I","aF":"NONE","sprite":"Bear","feature":"DistSnowballY"},"Node 14":{"id":14,"t":"I","aF":"NONE","sprite":"Rocks","feature":"X"},"Node 15":{"id":15,"t":"I","aF":"NONE","sprite":"Rocks","feature":"Y"},"Node 16":{"id":16,"t":"I","aF":"NONE","sprite":"Rocks","feature":"Dir"},"Node 17":{"id":17,"t":"I","aF":"NONE","sprite":"Rocks","feature":"Size"},"Node 18":{"id":18,"t":"I","aF":"NONE","sprite":"Rocks","feature":"DistBearX"},"Node 19":{"id":19,"t":"I","aF":"NONE","sprite":"Rocks","feature":"DistBearY"},"Node 20":{"id":20,"t":"B","aF":"NONE"},"Node 21":{"id":28,"t":"H","aF":"TANH"},"Node 22":{"id":29,"t":"H","aF":"TANH"},"Node 23":{"id":30,"t":"H","aF":"TANH"},"Node 24":{"id":31,"t":"H","aF":"TANH"},"Node 25":{"id":32,"t":"H","aF":"TANH"},"Node 26":{"id":33,"t":"H","aF":"TANH"},"Node 27":{"id":36,"t":"H","aF":"TANH"},"Node 28":{"id":90,"t":"H","aF":"TANH"},"Node 29":{"id":21,"t":"C","aF":"NONE","event":"MouseMoveEvent"},"Node 30":{"id":22,"t":"C","aF":"NONE","event":"KeyPressEvent-space"},"Node 31":{"id":23,"t":"C","aF":"NONE","event":"WaitEvent"},"Node 32":{"id":24,"t":"R","aF":"NONE","event":"MouseMoveEvent","eventP":"X"},"Node 33":{"id":25,"t":"R","aF":"NONE","event":"MouseMoveEvent","eventP":"Y"},"Node 34":{"id":26,"t":"R","aF":"NONE","event":"KeyPressEvent-space","eventP":"Steps"},"Node 35":{"id":27,"t":"R","aF":"NONE","event":"WaitEvent","eventP":"Duration"}},"Cons":{"Con 0":{"s":0,"t":28,"w":1.49508,"e":true,"i":0,"r":false},"Con 1":{"s":28,"t":21,"w":-0.04077,"e":true,"i":1,"r":false},"Con 2":{"s":28,"t":22,"w":-3.31843,"e":true,"i":2,"r":false},"Con 3":{"s":28,"t":23,"w":-0.24008,"e":true,"i":3,"r":false},"Con 4":{"s":28,"t":24,"w":1.52067,"e":true,"i":4,"r":false},"Con 5":{"s":28,"t":25,"w":-0.112,"e":false,"i":5,"r":false},"Con 6":{"s":28,"t":26,"w":-0.37447,"e":true,"i":6,"r":false},"Con 7":{"s":28,"t":27,"w":0.70857,"e":true,"i":7,"r":false},"Con 8":{"s":1,"t":29,"w":0.35054,"e":true,"i":8,"r":false},"Con 9":{"s":2,"t":29,"w":-0.36792,"e":true,"i":9,"r":false},"Con 10":{"s":3,"t":29,"w":-0.22601,"e":true,"i":10,"r":false},"Con 11":{"s":4,"t":29,"w":1.31316,"e":true,"i":11,"r":false},"Con 12":{"s":5,"t":29,"w":-2.46048,"e":true,"i":12,"r":false},"Con 13":{"s":6,"t":29,"w":-0.5714,"e":true,"i":13,"r":false},"Con 14":{"s":7,"t":29,"w":4.56216,"e":true,"i":14,"r":false},"Con 15":{"s":29,"t":21,"w":-0.85223,"e":false,"i":15,"r":false},"Con 16":{"s":29,"t":22,"w":0.30094,"e":true,"i":16,"r":false},"Con 17":{"s":29,"t":23,"w":3.70448,"e":true,"i":17,"r":false},"Con 18":{"s":29,"t":24,"w":0.44954,"e":true,"i":18,"r":false},"Con 19":{"s":29,"t":25,"w":-0.87201,"e":true,"i":19,"r":false},"Con 20":{"s":29,"t":26,"w":2.44581,"e":false,"i":20,"r":false},"Con 21":{"s":29,"t":27,"w":-0.42251,"e":true,"i":21,"r":false},"Con 22":{"s":8,"t":30,"w":2.4654,"e":true,"i":22,"r":false},"Con 23":{"s":9,"t":30,"w":-0.52865,"e":true,"i":23,"r":false},"Con 24":{"s":10,"t":30,"w":1.19532,"e":true,"i":24,"r":false},"Con 25":{"s":11,"t":30,"w":0.14887,"e":true,"i":25,"r":false},"Con 26":{"s":12,"t":30,"w":0.8887,"e":true,"i":26,"r":false},"Con 27":{"s":13,"t":30,"w":-4.83029,"e":true,"i":27,"r":false},"Con 28":{"s":30,"t":21,"w":-0.73936,"e":false,"i":28,"r":false},"Con 29":{"s":30,"t":22,"w":-3.30746,"e":false,"i":29,"r":false},"Con 30":{"s":30,"t":23,"w":0.05718,"e":true,"i":30,"r":false},"Con 31":{"s":30,"t":24,"w":-1.26543,"e":false,"i":31,"r":false},"Con 32":{"s":30,"t":25,"w":1.34826,"e":true,"i":32,"r":false},"Con 33":{"s":30,"t":26,"w":1.19001,"e":true,"i":33,"r":false},"Con 34":{"s":30,"t":27,"w":0.1543,"e":true,"i":34,"r":false},"Con 35":{"s":14,"t":31,"w":1.03709,"e":true,"i":35,"r":false},"Con 36":{"s":15,"t":31,"w":0.61507,"e":true,"i":36,"r":false},"Con 37":{"s":16,"t":31,"w":-2.66353,"e":true,"i":37,"r":false},"Con 38":{"s":17,"t":31,"w":1.37916,"e":false,"i":38,"r":false},"Con 39":{"s":18,"t":31,"w":0.79243,"e":true,"i":39,"r":false},"Con 40":{"s":19,"t":31,"w":-2.82956,"e":true,"i":40,"r":false},"Con 41":{"s":31,"t":21,"w":1.19137,"e":false,"i":41,"r":false},"Con 42":{"s":31,"t":22,"w":-0.34923,"e":true,"i":42,"r":false},"Con 43":{"s":31,"t":23,"w":0.46077,"e":true,"i":43,"r":false},"Con 44":{"s":31,"t":24,"w":-0.85057,"e":true,"i":44,"r":false},"Con 45":{"s":31,"t":25,"w":-1.27541,"e":true,"i":45,"r":false},"Con 46":{"s":31,"t":26,"w":0.43435,"e":true,"i":46,"r":false},"Con 47":{"s":31,"t":27,"w":2.20075,"e":true,"i":47,"r":false},"Con 48":{"s":20,"t":32,"w":0.38559,"e":true,"i":48,"r":false},"Con 49":{"s":32,"t":21,"w":-2.15485,"e":true,"i":49,"r":false},"Con 50":{"s":32,"t":22,"w":0.75646,"e":true,"i":50,"r":false},"Con 51":{"s":32,"t":23,"w":2.372,"e":true,"i":51,"r":false},"Con 52":{"s":32,"t":24,"w":1.60968,"e":false,"i":52,"r":false},"Con 53":{"s":32,"t":25,"w":1.13431,"e":false,"i":53,"r":false},"Con 54":{"s":32,"t":26,"w":-1.15961,"e":true,"i":54,"r":false},"Con 55":{"s":32,"t":27,"w":0.56361,"e":false,"i":55,"r":false},"Con 56":{"s":31,"t":33,"w":2.24591,"e":true,"i":59,"r":false},"Con 57":{"s":33,"t":27,"w":-0.70317,"e":true,"i":60,"r":false},"Con 58":{"s":29,"t":36,"w":1.3721,"e":true,"i":67,"r":false},"Con 59":{"s":36,"t":22,"w":0.55339,"e":true,"i":68,"r":false},"Con 60":{"s":14,"t":23,"w":-1.29821,"e":true,"i":374,"r":false},"Con 61":{"s":36,"t":90,"w":-0.1279,"e":true,"i":387,"r":false},"Con 62":{"s":90,"t":22,"w":1.81361,"e":true,"i":388,"r":false},"Con 63":{"s":29,"t":90,"w":-1.37776,"e":true,"i":430,"r":false},"Con 64":{"s":6,"t":90,"w":0.12093,"e":true,"i":434,"r":false}}}}}